Workbook

Sheet Summary
A1: TEST CASE SCENERIOS
A2: Covers: Order Management, Partial Order & Seller Processing, Roles & Permissions, Logistics & Delivery, Onboarding/Subscription/Commission, Pricing & Settlement, Reward Engine, Catalog/Search, Notifications & Post-Order, End-to-End Business Flows, New-Role Access (Delivery Partner/Operator/Finance), Integration, Exception/Negative, SEO, Performance/UX, Order Rescue & Reassignment, Order Restoration Management, and Dashboards & Analytics
A4: # | B4: Module / Sheet | C4: Total Test Cases | D4: High Priority | E4: Medium Priority | F4: Low Priority
A5: 1 | B5: Customer Order Mgmt | C5: ='Customer Order Mgmt'!$A$26 | D5: =COUNTIF('Customer Order Mgmt'!$J$3:$J$26,"High") | E5: =COUNTIF('Customer Order Mgmt'!$J$3:$J$26,"Medium") | F5: =COUNTIF('Customer Order Mgmt'!$J$3:$J$26,"Low")
A6: 2 | B6: Partial Order & Seller Ops | C6: ='Partial Order & Seller Ops'!$A$26 | D6: =COUNTIF('Partial Order & Seller Ops'!$J$3:$J$26,"High") | E6: =COUNTIF('Partial Order & Seller Ops'!$J$3:$J$26,"Medium") | F6: =COUNTIF('Partial Order & Seller Ops'!$J$3:$J$26,"Low")
A7: 3 | B7: Roles & Permissions | C7: ='Roles & Permissions'!$A$19 | D7: =COUNTIF('Roles & Permissions'!$J$3:$J$19,"High") | E7: =COUNTIF('Roles & Permissions'!$J$3:$J$19,"Medium") | F7: =COUNTIF('Roles & Permissions'!$J$3:$J$19,"Low")
A8: 4 | B8: Logistics & Delivery | C8: ='Logistics & Delivery'!$A$19 | D8: =COUNTIF('Logistics & Delivery'!$J$3:$J$19,"High") | E8: =COUNTIF('Logistics & Delivery'!$J$3:$J$19,"Medium") | F8: =COUNTIF('Logistics & Delivery'!$J$3:$J$19,"Low")
A9: 5 | B9: Onboarding, Subscription & Comm | C9: ='Onboarding, Subscription & Comm'!$A$17 | D9: =COUNTIF('Onboarding, Subscription & Comm'!$J$3:$J$17,"High") | E9: =COUNTIF('Onboarding, Subscription & Comm'!$J$3:$J$17,"Medium") | F9: =COUNTIF('Onboarding, Subscription & Comm'!$J$3:$J$17,"Low")
A10: 6 | B10: Pricing, Charges & Settlement | C10: ='Pricing, Charges & Settlement'!$A$16 | D10: =COUNTIF('Pricing, Charges & Settlement'!$J$3:$J$16,"High") | E10: =COUNTIF('Pricing, Charges & Settlement'!$J$3:$J$16,"Medium") | F10: =COUNTIF('Pricing, Charges & Settlement'!$J$3:$J$16,"Low")
A11: 7 | B11: Reward Engine | C11: ='Reward Engine'!$A$18 | D11: =COUNTIF('Reward Engine'!$J$3:$J$18,"High") | E11: =COUNTIF('Reward Engine'!$J$3:$J$18,"Medium") | F11: =COUNTIF('Reward Engine'!$J$3:$J$18,"Low")
A12: 8 | B12: Catalog, Search & Discovery | C12: ='Catalog, Search & Discovery'!$A$12 | D12: =COUNTIF('Catalog, Search & Discovery'!$J$3:$J$12,"High") | E12: =COUNTIF('Catalog, Search & Discovery'!$J$3:$J$12,"Medium") | F12: =COUNTIF('Catalog, Search & Discovery'!$J$3:$J$12,"Low")
A13: 9 | B13: Notifications & Post-Order | C13: ='Notifications & Post-Order'!$A$12 | D13: =COUNTIF('Notifications & Post-Order'!$J$3:$J$12,"High") | E13: =COUNTIF('Notifications & Post-Order'!$J$3:$J$12,"Medium") | F13: =COUNTIF('Notifications & Post-Order'!$J$3:$J$12,"Low")
A14: 10 | B14: E2E Business Flow | C14: ='E2E Business Flow'!$A$15 | D14: =COUNTIF('E2E Business Flow'!$J$3:$J$15,"High") | E14: =COUNTIF('E2E Business Flow'!$J$3:$J$15,"Medium") | F14: =COUNTIF('E2E Business Flow'!$J$3:$J$15,"Low")
A15: 11 | B15: Role-wise Testing (New Roles) | C15: ='Role-wise Testing (New Roles)'!$A$13 | D15: =COUNTIF('Role-wise Testing (New Roles)'!$J$3:$J$13,"High") | E15: =COUNTIF('Role-wise Testing (New Roles)'!$J$3:$J$13,"Medium") | F15: =COUNTIF('Role-wise Testing (New Roles)'!$J$3:$J$13,"Low")
A16: 12 | B16: Integration Testing | C16: ='Integration Testing'!$A$14 | D16: =COUNTIF('Integration Testing'!$J$3:$J$14,"High") | E16: =COUNTIF('Integration Testing'!$J$3:$J$14,"Medium") | F16: =COUNTIF('Integration Testing'!$J$3:$J$14,"Low")
A17: 13 | B17: Exception & Negative Testing | C17: ='Exception & Negative Testing'!$A$16 | D17: =COUNTIF('Exception & Negative Testing'!$J$3:$J$16,"High") | E17: =COUNTIF('Exception & Negative Testing'!$J$3:$J$16,"Medium") | F17: =COUNTIF('Exception & Negative Testing'!$J$3:$J$16,"Low")
A18: 14 | B18: SEO & Discoverability | C18: ='SEO & Discoverability'!$A$13 | D18: =COUNTIF('SEO & Discoverability'!$J$3:$J$13,"High") | E18: =COUNTIF('SEO & Discoverability'!$J$3:$J$13,"Medium") | F18: =COUNTIF('SEO & Discoverability'!$J$3:$J$13,"Low")
A19: 15 | B19: Performance & UX | C19: ='Performance & UX'!$A$10 | D19: =COUNTIF('Performance & UX'!$J$3:$J$10,"High") | E19: =COUNTIF('Performance & UX'!$J$3:$J$10,"Medium") | F19: =COUNTIF('Performance & UX'!$J$3:$J$10,"Low")
A20: 16 | B20: Order Rescue & Reassignment | C20: ='Order Rescue & Reassignment'!$A$20 | D20: =COUNTIF('Order Rescue & Reassignment'!$J$3:$J$20,"High") | E20: =COUNTIF('Order Rescue & Reassignment'!$J$3:$J$20,"Medium") | F20: =COUNTIF('Order Rescue & Reassignment'!$J$3:$J$20,"Low")
A21: 17 | B21: Order Restoration Mgmt | C21: ='Order Restoration Mgmt'!$A$19 | D21: =COUNTIF('Order Restoration Mgmt'!$J$3:$J$19,"High") | E21: =COUNTIF('Order Restoration Mgmt'!$J$3:$J$19,"Medium") | F21: =COUNTIF('Order Restoration Mgmt'!$J$3:$J$19,"Low")
A22: 18 | B22: Dashboards & Analytics | C22: ='Dashboards & Analytics'!$A$17 | D22: =COUNTIF('Dashboards & Analytics'!$J$3:$J$17,"High") | E22: =COUNTIF('Dashboards & Analytics'!$J$3:$J$17,"Medium") | F22: =COUNTIF('Dashboards & Analytics'!$J$3:$J$17,"Low")
A23: 19 | B23: extras | C23: 100 | D23: 79 | E23: 21 | F23: 0
B24: TOTAL | C24: =SUM(C5:C23) | D24: =SUM(D5:D23) | E24: =SUM(E5:E23) | F24: =SUM(F5:F23)
A26: Production Readiness — Additional Sheets
A27: Sheet | B27: Total Items | C27: Completed / Implemented | D27: Pending
A28: UAT Requirement Matrix | B28: =COUNTA('UAT Requirement Matrix'!$A$3:$A$23) | C28: =COUNTIF('UAT Requirement Matrix'!$F$3:$F$23,"Implemented") | D28: =COUNTIF('UAT Requirement Matrix'!$F$3:$F$23,"Pending Verification")
A29: Go-Live Sign-off Checklist | B29: =COUNTA('Go-Live Sign-off Checklist'!$A$3:$A$19) | C29: =COUNTIF('Go-Live Sign-off Checklist'!$D$3:$D$19,"Pass") | D29: =COUNTIF('Go-Live Sign-off Checklist'!$D$3:$D$19,"Pending")
A31: Legend
A32: • Priority: High = core business rule / revenue-or-compliance impact | Medium = important flow | Low = convenience feature
A33: • Type: Positive = expected/happy path | Negative = should be blocked/rejected | Edge = boundary or unusual condition
A34: • Status column supports dropdown: Not Executed / Pass / Fail / Blocked — update while executing test cycles
A35: • Test Case ID format: TC-<MODULE PREFIX>-<sequence> e.g. TC-ORD-001
A36: • New sheets added for Go-Live readiness: E2E Business Flow, Role-wise Testing (New Roles), Integration Testing, Exception & Negative Testing, SEO & Discoverability, Performance & UX, UAT Requirement Matrix, and Go-Live Sign-off Checklist.

Sheet Extras
A1: Extras — Test Case Scenarios
A2: S.No | B2: Test Case ID | C2: Module | D2: Sub-Feature / Flow | E2: Test Scenario | F2: Preconditions | G2: Test Steps | H2: Test Data | I2: Expected Result | J2: Priority | K2: Type | L2: Actor / Role | M2: Status
A3: 1 | B3: TC-USER-001 | C3: User | D3: Registration | E3: Register with valid details | F3: Registration page open | G3: Enter valid details → Submit | H3: Name, mobile, email, password | I3: Account should be created successfully | J3: High | K3: Functional | L3: User | M3: PASS
A4: 2 | B4: TC-USER-002 | C4: User | D4: Registration | E4: Register with existing mobile/email | F4: Account already exists | G4: Enter registered details → Submit | H4: Existing email/mobile | I4: Proper validation message should appear | J4: High | K4: Negative | L4: User | M4: PASS
A5: 3 | B5: TC-USER-003 | C5: User | D5: Login | E5: Login with valid credentials | F5: User registered | G5: Enter credentials → Login | H5: Valid credentials | I5: User should log in successfully | J5: High | K5: Functional | L5: User | M5: PASS
A6: 4 | B6: TC-USER-004 | C6: User | D6: Login | E6: Login with incorrect otp | F6: User registered | G6: Enter wrong otp → Login | H6: Invalid otp | I6: Login should fail | J6: High | K6: Negative | L6: User | M6: PASS
A7: 5 | B7: TC-USER-005 | C7: User | D7: Forgot Password | E7: Reset password | F7: User account exists | G7: Click Forgot Password → Verify OTP → Reset | H7: Valid OTP/new password | I7: Password should be reset successfully | J7: High | K7: Functional | L7: User | M7: FAIL | N7: removed password
A8: 6 | B8: TC-USER-006 | C8: User | D8: Profile | E8: Update profile | F8: User logged in | G8: Edit profile → Save | H8: Valid profile details | I8: Profile should be updated | J8: Medium | K8: Functional | L8: User | M8: PASS
A9: 7 | B9: TC-USER-007 | C9: User | D9: Address | E9: Add delivery address | F9: User logged in | G9: Add address → Save | H9: Valid address | I9: Address should be saved | J9: High | K9: Functional | L9: User | M9: PASS
A10: 8 | B10: TC-USER-008 | C10: User | D10: Address | E10: Edit saved address | F10: Address exists | G10: Edit address → Save | H10: Updated address | I10: Address should be updated | J10: Medium | K10: Functional | L10: User | M10: PASS
A11: 9 | B11: TC-USER-009 | C11: User | D11: Address | E11: Delete address | F11: Address exists | G11: Select address → Delete | H11: Existing address | I11: Address should be deleted | J11: Medium | K11: Functional | L11: User | M11: PASS
A12: 10 | B12: TC-USER-010 | C12: User | D12: Address | E12: Set default address | F12: Multiple addresses exist | G12: Select address → Set Default | H12: Saved address | I12: Selected address becomes default | J12: Medium | K12: Functional | L12: User | M12: PASS
A13: 11 | B13: TC-USER-011 | C13: User | D13: Product Search | E13: Search product by name | F13: Products exist | G13: Enter product name → Search | H13: "Shoes" | I13: Relevant products should appear | J13: High | K13: Functional | L13: User | M13: PASS
A14: 12 | B14: TC-USER-012 | C14: User | D14: Search | E14: Search with invalid keyword | F14: User logged in | G14: Search random keyword | H14: "XYZ123" | I14: No-result message should appear | J14: Medium | K14: Negative | L14: User | M14: PASS
A15: 13 | B15: TC-USER-013 | C15: User | D15: Category | E15: Browse products by category | F15: Categories exist | G15: Select category | H15: Electronics | I15: Correct products should appear | J15: High | K15: Functional | L15: User | M15: PASS
A16: 14 | B16: TC-USER-014 | C16: User | D16: Filter | E16: Filter by price | F16: Products exist | G16: Apply price filter | H16: ₹500–₹1,000 | I16: Only products within range should appear | J16: Medium | K16: Functional | L16: User | M16: FAIL
A17: 15 | B17: TC-USER-015 | C17: User | D17: Filter | E17: Filter by brand | F17: Multiple brands exist | G17: Select brand | H17: Nike | I17: Selected brand products displayed | J17: Medium | K17: Functional | L17: User | M17: FAIL
A18: 16 | B18: TC-USER-016 | C18: User | D18: Sort | E18: Sort products by price | F18: Products displayed | G18: Select Low to High | H18: Price | I18: Products sorted correctly | J18: Medium | K18: Functional | L18: User | M18: PASS
A19: 17 | B19: TC-USER-017 | C19: User | D19: Product Details | E19: View product details | F19: Product exists | G19: Open product | H19: Product ID | I19: Correct image, name, price, description and specifications displayed | J19: High | K19: Functional | L19: User | M19: PASS
... A102: 100 | B102: TC-E2E-100 | C102: Security | D102: Role Access | E102: Verify unauthorized panel access | F102: Multiple roles exist | G102: Attempt accessing another role's functions | H102: User/Seller/Admin accounts | I102: Unauthorized functions should be inaccessible | J102: High | K102: Security | L102: All Roles | M102: PASS

Sheet Customer Order Mgmt
A1: Customer Order Management — Test Case Scenarios
A2: S.No | B2: Test Case ID | C2: Module | D2: Sub-Feature / Flow | E2: Test Scenario | F2: Preconditions | G2: Test Steps | H2: Test Data | I2: Expected Result | J2: Priority | K2: Type | L2: Actor / Role | M2: Status
A3: 1 | B3: TC-ORD-001 | C3: Customer Order Management | D3: Regular Order | E3: Place a regular order successfully | F3: Customer logged in; shop is open; products in stock | G3: 1. Browse shop and add products to cart 2. Select delivery date = Today 3. Proceed to checkout and complete payment | H3: Valid product SKUs, valid UPI/card payment method | I3: Order placed successfully; status = 'Order Placed'; seller receives order notification; order visible in customer order history | J3: High | K3: Positive | L3: Customer | M3: PASS
A4: 2 | B4: TC-ORD-002 | C4: Customer Order Management | D4: Regular Order | E4: Attempt to add an out-of-stock product to cart | F4: Product stock = 0 | G4: 1. Search/browse for the out-of-stock product 2. Attempt to add to cart | H4: Product with stock quantity 0 | I4: Product is not displayed / not addable in customer app, per 'out-of-stock products hidden' rule | J4: High | K4: Negative | L4: Customer | M4: PASS
A5: 3 | B5: TC-ORD-003 | C5: Customer Order Management | D5: Regular Order | E5: Attempt to place order after 10 PM cut-off | F5: Current time is after 10:00 PM; platform order-timing restriction active | G5: 1. Add items to cart 2. Attempt checkout at 10:05 PM | H5: System clock/time = 22:05 | I5: Order placement is blocked; customer sees a message about the timing restriction (or order is auto-scheduled per odd-hour config) | J5: High | K5: Negative | L5: Customer | M5: PASS
A6: 4 | B6: TC-ORD-004 | C6: Customer Order Management | D6: Scheduled Order | E6: Place a scheduled order for a future date | F6: Seller supports scheduled orders; delivery calendar available | G6: 1. Add products to cart 2. Select a future delivery date from calendar 3. Complete payment | H6: Future date within seller's allowed scheduling range | I6: Order created with status 'Scheduled'; delivery date stored correctly; seller notified as a scheduled order | J6: High | K6: Positive | L6: Customer | M6: PASS
A7: 5 | B7: TC-ORD-005 | C7: Customer Order Management | D7: Scheduled Order | E7: Reschedule a scheduled order before seller's cut-off time | F7: Order is in 'Scheduled' state; current time before seller-defined cut-off | G7: 1. Open order 2. Select 'Reschedule' 3. Choose a new valid future date 4. Confirm | H7: New delivery date within valid window | I7: Order rescheduled successfully; customer receives confirmation message with new date | J7: Medium | K7: Positive | L7: Customer | M7: PASS
A8: 6 | B8: TC-ORD-006 | C8: Customer Order Management | D8: Scheduled Order | E8: Attempt to reschedule after cut-off time has passed | F8: Current time is past seller-defined cut-off for that scheduled order | G8: 1. Open scheduled order 2. Attempt to reschedule | H8: Cut-off time already elapsed | I8: Reschedule option disabled/blocked; system shows cut-off-passed message | J8: Medium | K8: Negative | L8: Customer | M8: PASS
A9: 7 | B9: TC-ORD-007 | C9: Customer Order Management | D9: Pre-Order | E9: Place a pre-order within an active campaign window | F9: Seller has published a pre-order campaign with a defined sale/delivery window | G9: 1. Browse pre-order section 2. Add pre-order product to cart 3. Select delivery date within campaign window 4. Complete payment | H9: Delivery date inside campaign window | I9: Order confirmed; awaits campaign sale-start date; delivery scheduled within campaign window only | J9: High | K9: Positive | L9: Customer | M9: PASS
A10: 8 | B10: TC-ORD-008 | C10: Customer Order Management | D10: Pre-Order | E10: Attempt to book a pre-order beyond the 1-month advance booking limit | F10: Pre-order product configured; advance booking capped at 1 month | G10: 1. Select pre-order product 2. Attempt to choose a delivery date more than 30 days out | H10: Delivery date = today + 45 days | I10: Date selection blocked/unavailable; system restricts to max 1-month advance window | J10: High | K10: Negative | L10: Customer | M10: PASS
A11: 9 | B11: TC-ORD-009 | C11: Customer Order Management | D11: Mixed Cart Order | E11: Cart with regular + pre-order item auto-aligns to future date | F11: Cart contains one regular (immediate) item and one pre-order item with a future date | G11: 1. Add a regular item to cart 2. Add a pre-order item to same cart 3. Proceed to cart/checkout | H11: Regular item (immediate) + Pre-order item (future date T+10) | I11: Cart page behaves as scheduling page; entire order aligned to the pre-order item's future delivery date; only valid dates for that item are selectable | J11: High | K11: Edge | L11: Customer | M11: PASS
A12: 10 | B12: TC-ORD-010 | C12: Customer Order Management | D12: Mixed Cart Order | E12: Cart with two pre-order items having different delivery windows | F12: Two different pre-order campaigns with non-overlapping delivery windows | G12: 1. Add pre-order item A (window: 5-10 Aug) 2. Add pre-order item B (window: 15-20 Aug) to same cart | H12: Item A + Item B, conflicting windows | I12: System detects conflicting scheduling windows and either blocks combined checkout or prompts to split into separate orders | J12: Medium | K12: Edge | L12: Customer | M12: PASS
A13: 11 | B13: TC-ORD-011 | C13: Customer Order Management | D13: Cart Modification | E13: Modify cart (add/remove items) before seller acceptance | F13: Order placed but not yet accepted by seller | G13: 1. Open order 2. Add an extra item / remove an item 3. Save changes | H13: Order in 'Placed'/'Seller Review' state | I13: Cart update succeeds; order total recalculated automatically | J13: High | K13: Positive | L13: Customer | M13: PASS
A14: 12 | B14: TC-ORD-012 | C14: Customer Order Management | D14: Cart Modification | E14: Attempt direct cart edit after seller acceptance | F14: Order already accepted by seller | G14: 1. Open accepted order 2. Attempt to add/remove item directly | H14: Order in 'Accepted' state | I14: Direct edit is disabled; customer is redirected to raise a modification/reschedule request instead | J14: High | K14: Negative | L14: Customer | M14: PASS
... A26: 24 | B26: TC-ORD-024 | C26: Customer Order Management | D26: Wallet & Revised Bill | E26: Wallet balance insufficient to cover a price-revised bill | F26: Seller has issued a revised (higher) bill after replacement/price increase; customer wallet balance < difference | G26: 1. Seller revises bill upward 2. Customer notified to pay difference 3. Customer attempts payment with insufficient wallet balance | H26: Wallet balance = ₹50; amount due = ₹120 | I26: System prompts alternate payment method (UPI/card) for the shortfall; order remains 'Awaiting Additional Payment' until resolved | J26: High | K26: Edge | L26: Customer | M26: PASS

Sheet Partial Order & Seller Ops
A1: Partial Order & Seller Processing — Test Case Scenarios
A2: S.No | B2: Test Case ID | C2: Module | D2: Sub-Feature / Flow | E2: Test Scenario | F2: Preconditions | G2: Test Steps | H2: Test Data | I2: Expected Result | J2: Priority | K2: Type | L2: Actor / Role | M2: Status
A3: 1 | B3: TC-PART-001 | C3: Partial Order & Seller Processing | D3: Inventory Review | E3: Seller reviews inventory - all items available - accepts order | F3: New order received by seller | G3: 1. Seller opens new order 2. Checks product availability 3. Taps 'Accept Order' | H3: All items in stock | I3: Order accepted; status moves to 'Preparing'; customer notified | J3: High | K3: Positive | L3: Seller | M3: PASS
A4: 2 | B4: TC-PART-002 | C4: Partial Order & Seller Processing | D4: Inventory Review | E4: Seller reviews inventory - some items unavailable - triggers partial-order decision | F4: New order received; one or more items out of stock | G4: 1. Seller opens order 2. Checks availability 3. System flags unavailable item(s) | H4: Order with 4 items, 1 unavailable | I4: Seller is routed to Partial Order Decision screen (Cancel / Split / Replace / Reject options) | J4: High | K4: Positive | L4: Seller | M4: FAIL
A5: 3 | B5: TC-PART-003 | C5: Partial Order & Seller Processing | D5: Partial Cancellation | E5: Seller partially cancels unavailable item and continues remaining order | F5: Order flagged with unavailable item(s) | G5: 1. Select 'Partial Cancellation' 2. Choose unavailable item(s) 3. Confirm cancellation of selected items only | H5: 1 of 4 items unavailable | I5: Selected item cancelled; wallet refund auto-generated for that item; settlement recalculated; remaining order proceeds | J5: High | K5: Positive | L5: Seller | M5: FAIL
A6: 4 | B6: TC-PART-004 | C6: Partial Order & Seller Processing | D6: Split Delivery | E6: Split delivery - available items today, remainder scheduled next day | F6: Order has both available and unavailable-until-tomorrow items | G6: 1. Select 'Split Delivery' 2. Confirm items for today 3. Schedule remaining items for next delivery 4. Send for customer confirmation | H6: 2 items available now, 2 arriving tomorrow | I6: Two separate delivery records created; customer notified and must confirm before dispatch | J6: High | K6: Positive | L6: Seller | M6: PASS
A7: 5 | B7: TC-PART-005 | C7: Partial Order & Seller Processing | D7: Split Delivery | E7: Additional logistics charge applied and requires customer confirmation | F7: Split delivery selected; extra delivery run needed | G7: 1. Seller applies additional delivery charge for second trip 2. Sends revised bill to customer | H7: Extra delivery fee = ₹25 | I7: Customer sees revised bill with added charge and must confirm before split order proceeds | J7: Medium | K7: Positive | L7: Seller | M7: PASS
A8: 6 | B8: TC-PART-006 | C8: Partial Order & Seller Processing | D8: Split Delivery | E8: Customer rejects the additional split-delivery charge | F8: Revised bill with extra logistics charge sent to customer | G8: 1. Customer opens revised bill 2. Taps 'Reject' | H8: Extra delivery fee proposed | I8: Split delivery is not confirmed; seller must offer an alternative (e.g., cancel unavailable item, full split at no charge if configured) | J8: Medium | K8: Negative | L8: Seller | M8: PASS
A9: 7 | B9: TC-PART-007 | C9: Partial Order & Seller Processing | D9: Product Replacement | E9: Seller suggests replacement and customer approves | F9: Item unavailable; alternative in stock | G9: 1. Seller selects 'Product Replacement' 2. Suggests alternate product 3. Sends to customer for approval 4. Customer approves | H9: Original ₹250 item replaced with ₹250 alternative | I9: Order continues with replacement item; invoice updated; no price impact (equal price) | J9: High | K9: Positive | L9: Seller | M9: PASS
A10: 8 | B10: TC-PART-008 | C10: Partial Order & Seller Processing | D10: Product Replacement | E10: Customer rejects replacement - partial refund issued | F10: Replacement suggested but rejected by customer | G10: 1. Customer reviews replacement 2. Taps 'Reject' | H10: Unavailable item value = ₹250 | I10: Unavailable item cancelled; ₹250 refunded to wallet; order continues with remaining items | J10: High | K10: Positive | L10: Seller | M10: PASS
A11: 9 | B11: TC-PART-009 | C11: Partial Order & Seller Processing | D11: Reject Order | E11: Reject complete order - entire inventory unavailable | F11: All items in the order are unavailable / seller cannot fulfill | G11: 1. Seller selects 'Reject Complete Order' 2. Confirms rejection with reason | H11: Entire cart unavailable | I11: Full refund issued to customer wallet; order status = 'Closed'; customer notified with reason | J11: High | K11: Positive | L11: Seller | M11: PASS
A12: 10 | B12: TC-PART-010 | C12: Partial Order & Seller Processing | D12: Revised Invoice | E12: Revised invoice generated correctly after partial cancellation | F12: Partial cancellation processed | G12: 1. Complete partial cancellation flow 2. Open generated invoice | H12: Original order ₹1,245; 1 item (₹60) cancelled | I12: Revised invoice reflects new total (₹1,185) with itemized breakup and cancellation note | J12: High | K12: Positive | L12: Seller | M12: PASS
A13: 11 | B13: TC-PART-011 | C13: Partial Order & Seller Processing | D13: Price Adjustment | E13: Replacement item priced higher - customer pays difference | F13: Replacement item costs more than original | G13: 1. Seller suggests higher-priced replacement 2. Customer approves 3. System calculates price difference | H13: Original ₹100 -> Replacement ₹130 | I13: Customer prompted to pay ₹30 difference via wallet/UPI/card before order proceeds | J13: High | K13: Positive | L13: Seller | M13: PASS
A14: 12 | B14: TC-PART-012 | C14: Partial Order & Seller Processing | D14: Price Adjustment | E14: Replacement item priced lower - refund credited to wallet | F14: Replacement item costs less than original | G14: 1. Seller suggests lower-priced replacement 2. Customer approves | H14: Original ₹150 -> Replacement ₹120 | I14: ₹30 automatically credited to customer wallet; settlement updated | J14: High | K14: Positive | L14: Seller | M14: PASS
... A26: 24 | B26: TC-PART-024 | C26: Partial Order & Seller Processing | D26: Dispute Resolution | E26: Super Admin resolves a customer dispute | F26: Open complaint/dispute linked to an order | G26: 1. Super Admin reviews complaint details 2. Coordinates with seller/customer 3. Records resolution | H26: Dispute over damaged/missing item | I26: Dispute marked resolved with outcome (refund/replacement/rejection) and reason logged | J26: Medium | K26: Positive | L26: Super Admin | M26: PASS

Sheet Roles & Permissions
A1: Roles & Permissions — Test Case Scenarios
A2: S.No | B2: Test Case ID | C2: Module | D2: Sub-Feature / Flow | E2: Test Scenario | F2: Preconditions | G2: Test Steps | H2: Test Data | I2: Expected Result | J2: Priority | K2: Type | L2: Actor / Role | M2: Status
A3: 1 | B3: TC-ROLE-001 | C3: Roles & Permissions | D3: Customer Permissions | E3: Customer modifies order freely before seller acceptance | F3: Order not yet accepted | G3: 1. Customer opens order 2. Adds/removes items, changes quantity, or cancels | H3: Order in 'Placed' state | I3: All modification actions succeed without seller intervention | J3: High | K3: Positive | L3: Customer | M3: PASS
A4: 2 | B4: TC-ROLE-002 | C4: Roles & Permissions | D4: Customer Permissions | E4: Customer attempts direct edit after seller acceptance | F4: Order accepted | G4: 1. Customer attempts to directly modify accepted order | H4: Order in 'Accepted' state | I4: Direct edit disabled; only 'Raise Request' options (Modify/Reschedule/Partial Cancel) available | J4: High | K4: Negative | L4: Customer | M4: PASS
A5: 3 | B5: TC-ROLE-003 | C5: Roles & Permissions | D5: Seller (Admin) Access | E5: Seller (Shop Admin) has full access to shop settings and finance | F5: Seller logged into Seller Hub | G5: 1. Navigate through Dashboard, Orders, Products, Finance, Subscription, Assistants, Settings | H5: Seller/Admin account | I5: Full access granted to all modules including Finance & Payouts, Subscription, and Assistant management | J5: Medium | K5: Positive | L5: Seller | M5: PASS
A6: 4 | B6: TC-ROLE-004 | C6: Roles & Permissions | D6: Assistant Creation | E6: Seller creates an assistant and assigns shop-wise permission | F6: Seller account with at least one shop | G6: 1. Seller opens 'Assistants' 2. Adds new assistant 3. Assigns to specific shop(s) 4. Sets role/permission level | H6: New assistant, assigned to Shop 1 only, Operational role | I6: Assistant account created with restricted access limited to Shop 1 and Operational-level actions | J6: High | K6: Positive | L6: Seller | M6: PASS
A7: 5 | B7: TC-ROLE-005 | C7: Roles & Permissions | D7: Assistant - View Only | E7: Assistant with View-Only permission attempts to modify an order | F7: Assistant assigned View-Only role | G7: 1. Assistant logs in 2. Opens order 3. Attempts to accept/modify | H7: View-Only role | I7: Action blocked; assistant can only view data, not perform operations | J7: High | K7: Negative | L7: Assistant | M7: PASS
A8: 6 | B8: TC-ROLE-006 | C8: Roles & Permissions | D8: Assistant - Operational | E8: Assistant with Operational permission accepts and modifies an order | F8: Assistant assigned Operational role | G8: 1. Assistant logs in 2. Accepts order, updates stock, modifies orders | H8: Operational role | I8: Actions succeed for allowed categories (orders/inventory); finance-related actions remain blocked | J8: Medium | K8: Positive | L8: Assistant | M8: PASS
A9: 7 | B9: TC-ROLE-007 | C9: Roles & Permissions | D9: Assistant - Full Operation | E9: Assistant with Full Operation permission performs all order actions except finance | F9: Assistant assigned Full Operation role | G9: 1. Assistant performs accept/reject, split delivery, replace product, reschedule 2. Attempts finance action | H9: Full Operation role | I9: All operational actions succeed; finance/settlement/subscription actions remain blocked | J9: Medium | K9: Positive | L9: Assistant | M9: PASS
A10: 8 | B10: TC-ROLE-008 | C10: Roles & Permissions | D10: Assistant Restrictions | E10: Assistant (any level) attempts to access Finance & Payouts | F10: Assistant of any permission level | G10: 1. Assistant navigates to Finance & Payouts section | H10: Any assistant role | I10: Access denied - 'No Access (Restricted)' regardless of assigned permission level | J10: High | K10: Negative | L10: Assistant | M10: FAIL
A11: 9 | B11: TC-ROLE-009 | C11: Roles & Permissions | D11: Assistant Restrictions | E11: Assistant attempts to add/remove another assistant | F11: Assistant of any permission level | G11: 1. Assistant opens 'Assistants' module 2. Attempts to add/remove an assistant | H11: Any assistant role | I11: Action blocked; only Seller (Admin) can manage assistants | J11: High | K11: Negative | L11: Assistant | M11: PASS
A12: 10 | B12: TC-ROLE-010 | C12: Roles & Permissions | D12: Assistant Restrictions | E12: Assistant attempts to change their own role/permission | F12: Assistant logged in | G12: 1. Assistant navigates to their own profile/permission settings 2. Attempts to change role | H12: Any assistant role | I12: Action blocked; only Seller can set/change assistant roles and permissions | J12: High | K12: Negative | L12: Assistant | M12: PASS
A13: 11 | B13: TC-ROLE-011 | C13: Roles & Permissions | D13: Access Revocation | E13: Seller disables an assistant's access | F13: Active assistant with granted permissions | G13: 1. Seller opens Assistants list 2. Toggles 'Disable Access' for an assistant | H13: Active assistant | I13: Assistant immediately loses access on next action/login attempt; seller can re-enable anytime | J13: Medium | K13: Positive | L13: Seller | M13: PASS
A14: 12 | B14: TC-ROLE-012 | C14: Roles & Permissions | D14: Super Admin Oversight | E14: Super Admin views complete audit logs across all sellers | F14: Super Admin logged in | G14: 1. Navigate to Audit Logs 2. Filter by seller/date/action type | H14: Multiple sellers with transaction history | I14: Complete, filterable audit trail displayed across all sellers and shops | J14: Medium | K14: Positive | L14: Super Admin | M14: FAIL
... A19: 17 | B19: TC-ROLE-017 | C19: Roles & Permissions | D19: Multi-Assistant Isolation | E19: Multiple assistants assigned to different shops maintain isolated access | F19: Seller has 2+ shops, each with a different assistant assigned | G19: 1. Assistant A (Shop 1) logs in 2. Attempts to view/act on Shop 2 orders | H19: Assistant A assigned only to Shop 1 | I19: Assistant A cannot view or act on Shop 2 data; strict shop-wise data isolation enforced | J19: High | K19: Edge | L19: Assistant | M19: PASS

Sheet Onboarding, Subscription & Comm
A1: Seller Onboarding, Subscription & Commission — Test Case Scenarios
A2: S.No | B2: Test Case ID | C2: Module | D2: Sub-Feature / Flow | E2: Test Scenario | F2: Preconditions | G2: Test Steps | H2: Test Data | I2: Expected Result | J2: Priority | K2: Type | L2: Actor / Role | M2: Status
A3: 1 | B3: TC-SUB-001 | C3: Seller Onboarding, Subscription & Commission | D3: Onboarding | E3: Seller registers and submits KYC documents | F3: New user registered as customer/user | G3: 1. User taps 'Become a Seller' 2. Fills business details 3. Uploads PAN/GST/Bank documents 4. Submits application | H3: Valid PAN, GST, bank details | I3: Application submitted with status 'KYC Pending' | J3: High | K3: Positive | L3: Seller | M3: PASS
A4: 2 | B4: TC-SUB-002 | C4: Seller Onboarding, Subscription & Commission | D4: Onboarding | E4: Admin verifies and approves seller KYC | F4: Seller has submitted KYC documents | G4: 1. Admin opens pending KYC queue 2. Reviews documents 3. Approves | H4: Complete and valid documents | I4: Seller status changes to 'Approved'; seller can proceed to subscribe/create shop | J4: High | K4: Positive | L4: Admin | M4: PASS
A5: 3 | B5: TC-SUB-003 | C5: Seller Onboarding, Subscription & Commission | D5: Onboarding | E5: Admin rejects seller KYC with reason | F5: Seller has submitted KYC documents with issues | G5: 1. Admin reviews documents 2. Rejects with a reason (e.g., mismatched GST) | H5: Invalid/incomplete GST document | I5: Seller notified of rejection with reason; can resubmit corrected documents | J5: Medium | K5: Negative | L5: Admin | M5: PASS
A6: 4 | B6: TC-SUB-004 | C6: Seller Onboarding, Subscription & Commission | D6: Subscription Model | E6: Seller chooses Subscription Model and selects a plan | F6: Seller approved and reached 'Choose Business Model' step | G6: 1. Seller selects 'Subscription Model' 2. Chooses shop count, product limit, duration 3. Proceeds to payment | H6: Premium Monthly plan: 3 shops, 100 products/shop, 1 month, ₹1,499 | I6: Plan selected and moved to payment step with correct amount displayed | J6: High | K6: Positive | L6: Seller | M6: PASS
A7: 5 | B7: TC-SUB-005 | C7: Seller Onboarding, Subscription & Commission | D7: Subscription Model | E7: Seller completes payment - instant activation | F7: Plan selected, payment initiated | G7: 1. Seller completes payment via UPI/card/wallet | H7: Payment amount = ₹1,499 | I7: Subscription activated instantly; shops/products enabled up to purchased limits; seller can start receiving orders | J7: High | K7: Positive | L7: Seller | M7: PASS
A8: 6 | B8: TC-SUB-006 | C8: Seller Onboarding, Subscription & Commission | D8: Subscription Expiry | E8: Subscription expires - shops/products auto-hidden | F8: Active subscription reaches its end date without renewal | G8: 1. Let subscription expiry date pass without renewal 2. Check shop/product visibility on customer app | H8: Subscription end date = today | I8: Shops and products automatically hidden from customer app; no new orders accepted; existing orders still fulfillable | J8: High | K8: Negative | L8: System | M8: PASS
A9: 7 | B9: TC-SUB-007 | C9: Seller Onboarding, Subscription & Commission | D9: Subscription Renewal | E9: Seller renews an expired subscription | F9: Subscription expired; shops hidden | G9: 1. Seller opens Subscription module 2. Renews or upgrades plan 3. Completes payment | H9: Renewal of expired Premium Monthly plan | I9: Shops and products become visible again instantly; orders can resume | J9: High | K9: Positive | L9: Seller | M9: PASS
A10: 8 | B10: TC-SUB-008 | C10: Seller Onboarding, Subscription & Commission | D10: Commission Model | E10: Seller exceeds 30-product limit without subscription | F10: Seller on base (non-subscribed) model with 30 products already listed | G10: 1. Seller attempts to add the 31st product without an active subscription | H10: 30 existing products, no subscription | I10: Seller is prompted to subscribe, OR higher commission rate is automatically applied to continue selling beyond the limit | J10: High | K10: Edge | L10: Seller | M10: PASS
A11: 9 | B11: TC-SUB-009 | C11: Seller Onboarding, Subscription & Commission | D11: Commission Model | E11: Seller opts for Commission Model instead of Subscription | F11: Seller approved and reached 'Choose Business Model' step | G11: 1. Seller selects 'Commission Model' 2. Sets selling price (commission auto-included) 3. Starts selling with no upfront fee | H11: Input price ₹100, commission 10% -> Customer price ₹120 | I11: Seller can start listing/selling immediately with no upfront payment; commission deducted at settlement | J11: High | K11: Positive | L11: Seller | M11: PASS
A12: 10 | B12: TC-SUB-010 | C12: Seller Onboarding, Subscription & Commission | D12: Commission Calculation | E12: Commission is calculated correctly at category/shop/product level | F12: Multiple commission rules configured (e.g., 10% Electronics, 5% Grocery) | G12: 1. Place orders across different categories 2. Check calculated commission per order | H12: Electronics order ₹1,000 (10%); Grocery order ₹500 (5%) | I12: Commission of ₹100 applied to Electronics order and ₹25 to Grocery order respectively | J12: High | K12: Positive | L12: System | M12: PASS
A13: 11 | B13: TC-SUB-011 | C13: Seller Onboarding, Subscription & Commission | D13: Plan Management | E13: Seller upgrades subscription plan to increase shop/product capacity | F13: Active subscription nearing shop/product limit | G13: 1. Seller opens Subscription 2. Selects 'Upgrade Plan' 3. Chooses higher tier 4. Pays difference | H13: Basic Monthly (1 shop) -> Premium Monthly (3 shops) | I13: Plan upgraded; new shop/product limits immediately available | J13: Medium | K13: Positive | L13: Seller | M13: FAIL
A14: 12 | B14: TC-SUB-012 | C14: Seller Onboarding, Subscription & Commission | D14: Shop Limit | E14: Seller adds multiple shops within subscribed limit | F14: Active subscription allows up to 3 shops; seller currently has 1 | G14: 1. Seller creates Shop 2 2. Creates Shop 3 | H14: Plan limit = 3 shops | I14: Both additional shops created successfully, each independently configurable | J14: Medium | K14: Positive | L14: Seller | M14: PASS
... A17: 15 | B17: TC-SUB-015 | C17: Seller Onboarding, Subscription & Commission | D17: Seller Referral | E17: New seller is rewarded after KYC approval and subscription purchase | F17: Existing seller refers a new seller via referral link/code | G17: 1. New seller registers using referral code 2. Completes KYC 3. Purchases a subscription | H17: Valid, non-duplicate referral code | I17: Referral reward credited to referring seller once both KYC approval and subscription purchase are complete | J17: Medium | K17: Positive | L17: System | M17: PASS

Sheet Pricing, Charges & Settlement
A1: Pricing, Charges, Invoice & Settlement — Test Case Scenarios
A2: S.No | B2: Test Case ID | C2: Module | D2: Sub-Feature / Flow | E2: Test Scenario | F2: Preconditions | G2: Test Steps | H2: Test Data | I2: Expected Result | J2: Priority | K2: Type | L2: Actor / Role | M2: Status
A3: 1 | B3: TC-PRC-001 | C3: Pricing, Charges, Invoice & Settlement | D3: Invoice Breakup | E3: Invoice generated with correct component breakup | F3: Order completed with product cost, GST, delivery fee, handling fee applicable | G3: 1. Place and complete an order 2. Open generated invoice | H3: Product ₹1,050; GST ₹0 (exempt); Delivery ₹40; Handling ₹15 | I3: Invoice shows itemized breakup summing correctly to Grand Total (₹1,105) | J3: High | K3: Positive | L3: System | M3: PASS
A4: 2 | B4: TC-PRC-002 | C4: Pricing, Charges, Invoice & Settlement | D4: Odd-Hour Charges | E4: Odd-hour surcharge applied for a late-night order | F4: Odd-hour charge configured by admin (e.g., 10 PM - 6 AM) | G4: 1. Place an order at 11 PM (within odd-hour window, if allowed) 2. Check invoice for surcharge | H4: Odd-hour surcharge = ₹15 | I4: Surcharge correctly added to invoice as a separate line item | J4: Medium | K4: Positive | L4: System | M4: PASS
A5: 3 | B5: TC-PRC-003 | C5: Pricing, Charges, Invoice & Settlement | D5: Weather Surcharge | E5: Bad-weather surcharge applied when configured | F5: Admin has enabled a weather surcharge for the region | G5: 1. Enable weather surcharge in admin panel 2. Place an order 3. Check invoice | H5: Weather surcharge = ₹10 | I5: Surcharge reflected correctly in the invoice and included in customer payment | J5: Medium | K5: Positive | L5: System | M5: PASS
A6: 4 | B6: TC-PRC-004 | C6: Pricing, Charges, Invoice & Settlement | D6: Packaging Charges | E6: Packaging charge varies correctly by product category | F6: Category-based packaging charge configured (e.g., sweet boxes cost more to pack) | G6: 1. Order a standard item and a sweet-box item 2. Compare packaging charges on invoice | H6: Standard packaging ₹5; Sweet-box packaging ₹20 | I6: Each item's packaging charge matches its category-specific configured rate | J6: Medium | K6: Positive | L6: System | M6: PASS
A7: 5 | B7: TC-PRC-005 | C7: Pricing, Charges, Invoice & Settlement | D7: Platform Fee | E7: Platform fee applied conditionally per configuration | F7: Admin has configured platform fee to apply above/below a threshold | G7: 1. Place an order below threshold 2. Place an order above threshold 3. Compare invoices | H7: Threshold = ₹200; Fee = ₹10 if order < ₹200 | I7: Platform fee applied only when the condition is met, per configured rule | J7: Medium | K7: Positive | L7: System | M7: FAIL
A8: 6 | B8: TC-PRC-006 | C8: Pricing, Charges, Invoice & Settlement | D8: GST Invoice | E8: GST invoice auto-generated for customer and seller | F8: Order completed successfully | G8: 1. Complete an order 2. Check customer app and seller portal for GST invoice | H8: GST-applicable order | I8: GST invoice generated and downloadable/viewable by both customer and seller with correct tax breakup | J8: High | K8: Positive | L8: System | M8: PASS
A9: 7 | B9: TC-PRC-007 | C9: Pricing, Charges, Invoice & Settlement | D9: Seller Settlement | E9: Settlement calculated after deducting commission, GST, and refunds | F9: Order delivered; commission and GST applicable; no disputes | G9: 1. Complete order lifecycle to 'Delivered' 2. Check seller settlement entry | H9: Order ₹1,000; commission 10%; GST already included | I9: Settlement shows ₹900 payable to seller (after ₹100 commission deduction), correctly itemized | J9: High | K9: Positive | L9: System | M9: FAIL
A10: 8 | B10: TC-PRC-008 | C10: Pricing, Charges, Invoice & Settlement | D10: Settlement Hold | E10: Settlement is held due to an open complaint/dispute | F10: Delivered order has an active customer complaint | G10: 1. Customer raises complaint within 24-hr window 2. Check settlement status for that order | H10: Open complaint on delivered order | I10: Settlement status shows 'On Hold' until dispute is resolved | J10: High | K10: Edge | L10: System | M10: PASS
A11: 9 | B11: TC-PRC-009 | C11: Pricing, Charges, Invoice & Settlement | D11: Settlement Release | E11: Settlement released after dispute is resolved | F11: Previously held settlement; dispute now resolved by Super Admin | G11: 1. Super Admin resolves the complaint 2. Check settlement status | H11: Resolved dispute, no refund due | I11: Settlement moves from 'On Hold' to 'Settled'/'Processing' as applicable | J11: Medium | K11: Positive | L11: System | M11: PASS
A12: 10 | B12: TC-PRC-010 | C12: Pricing, Charges, Invoice & Settlement | D12: Bulk Order Settlement | E12: Bulk order settlement calculated with its own commission rule | F12: Bulk-order-specific commission/margin rule configured | G12: 1. Place a bulk order 2. Complete delivery 3. Check settlement breakdown | H12: Bulk order value ₹50,000; bulk commission rate 6% (vs standard 10%) | I12: Settlement applies the bulk-specific commission rate, shown distinctly in admin's settlement breakdown | J12: Medium | K12: Positive | L12: System | M12: PASS
A13: 11 | B13: TC-PRC-011 | C13: Pricing, Charges, Invoice & Settlement | D13: Price Revision | E13: Price increase - customer must pay difference before processing continues | F13: Seller has revised the bill upward (e.g., due to replacement) | G13: 1. Seller sends revised bill 2. Customer notified 3. Customer pays the difference | H13: Difference amount = ₹40 | I13: Order proceeds only after additional payment is confirmed; status reflects 'Awaiting Additional Payment' until then | J13: High | K13: Positive | L13: System | M13: PASS
A14: 12 | B14: TC-PRC-012 | C14: Pricing, Charges, Invoice & Settlement | D14: Price Revision | E14: Price decrease - wallet credited automatically | F14: Seller has revised the bill downward | G14: 1. Seller sends revised (lower) bill 2. System processes automatically | H14: Difference amount = ₹25 | I14: ₹25 automatically credited to customer wallet without requiring customer action | J14: Medium | K14: Positive | L14: System | M14: FAIL
... A16: 14 | B16: TC-PRC-014 | C16: Pricing, Charges, Invoice & Settlement | D16: Wallet Shortfall | E16: Wallet balance insufficient to cover a price difference | F16: Wallet balance less than the amount due after a price increase | G16: 1. Trigger a price increase scenario 2. Attempt payment using wallet only | H16: Wallet balance ₹20; amount due ₹60 | I16: System blocks wallet-only payment and prompts for a supplementary payment method to cover the shortfall | J16: High | K16: Edge | L16: System | M16: PASS

Sheet Logistics & Delivery
A1: Logistics & Delivery Management — Test Case Scenarios
A2: S.No | B2: Test Case ID | C2: Module | D2: Sub-Feature / Flow | E2: Test Scenario | F2: Preconditions | G2: Test Steps | H2: Test Data | I2: Expected Result | J2: Priority | K2: Type | L2: Actor / Role | M2: Status
A3: 1 | B3: TC-LOG-001 | C3: Logistics & Delivery Management | D3: Self Pickup | E3: Seller enables Self Pickup only | F3: Seller configures shop delivery policy | G3: 1. Seller turns ON Self Pickup, turns OFF Self/Platform Delivery 2. Customer views shop | H3: Shop policy: Pickup=ON, Others=OFF | I3: Customer sees only 'Customer Pickup' as a fulfillment option at checkout | J3: High | K3: Positive | L3: Seller | M3: PASS
A4: 2 | B4: TC-LOG-002 | C4: Logistics & Delivery Management | D4: Self Delivery | E4: Order delivered using seller's own delivery resources | F4: Self (Seller) Delivery enabled for shop | G4: 1. Customer selects Self Delivery at checkout 2. Seller accepts and dispatches own rider | H4: Self Delivery = ON | I4: Order delivered by seller's own resources; customer pays delivery charge as configured by seller | J4: High | K4: Positive | L4: Seller | M4: FAIL
A5: 3 | B5: TC-LOG-003 | C5: Logistics & Delivery Management | D5: Platform Logistics | E5: Super Admin enables Platform Logistics on behalf of seller | F5: Seller has requested Platform Logistics | G5: 1. Super Admin opens seller's logistics config 2. Enables Platform Logistics, sets service area/charges | H5: Seller shop requesting platform logistics | I5: Platform Logistics becomes available as a fulfillment option for that shop's customers | J5: High | K5: Positive | L5: Super Admin | M5: PASS
A6: 4 | B6: TC-LOG-004 | C6: Logistics & Delivery Management | D6: Platform Logistics | E6: Delivery partner assigned only after seller accepts order | F6: Customer selected Platform Logistics; order pending seller acceptance | G6: 1. Customer places order with Platform Logistics 2. Seller accepts order 3. Observe delivery partner assignment | H6: Platform Logistics enabled | I6: Delivery partner is assigned only after seller acceptance, not before; customer address shared only post-acceptance | J6: High | K6: Positive | L6: Platform/Seller | M6: PASS
A7: 5 | B7: TC-LOG-005 | C7: Logistics & Delivery Management | D7: No Option Available | E7: All logistics options disabled or unavailable | F7: Shop has Pickup, Self Delivery, and Platform Logistics all OFF/unavailable | G7: 1. Customer attempts to place order for that shop | H7: All fulfillment options disabled | I7: System shows 'No Option Available'; order cannot be delivered; customer notified accordingly | J7: High | K7: Negative | L7: System | M7: PASS
A8: 6 | B8: TC-LOG-006 | C8: Logistics & Delivery Management | D8: No Option Available | E8: Customer address is outside the configured delivery radius | F8: Shop delivery radius configured; customer address outside range | G8: 1. Customer attempts checkout from an out-of-radius address | H8: Delivery radius = 5 km; customer at 8 km | I8: Delivery marked unavailable for that address; customer informed order cannot be delivered | J8: High | K8: Edge | L8: System | M8: PASS
A9: 7 | B9: TC-LOG-007 | C9: Logistics & Delivery Management | D9: Pickup Verification | E9: Customer pickup verified via OTP | F9: Order marked 'Ready for Pickup' | G9: 1. Customer arrives at shop 2. Provides OTP to seller 3. Seller verifies | H9: Valid pickup OTP | I9: Pickup verified and order marked 'Delivered/Completed' | J9: Medium | K9: Positive | L9: Seller/Customer | M9: PASS
A10: 8 | B10: TC-LOG-008 | C10: Logistics & Delivery Management | D10: Pickup Verification | E10: Customer pickup verified via QR Code | F10: Order marked 'Ready for Pickup' | G10: 1. Customer shows QR code 2. Seller scans code to verify | H10: Valid pickup QR | I10: Pickup verified successfully; order completed | J10: Medium | K10: Positive | L10: Seller/Customer | M10: PASS
A11: 9 | B11: TC-LOG-009 | C11: Logistics & Delivery Management | D11: Pickup Verification | E11: Invalid OTP entered during pickup verification | F11: Order marked 'Ready for Pickup' | G11: 1. Customer/representative enters an incorrect OTP | H11: Invalid OTP | I11: Verification fails; pickup not marked complete; retry allowed within attempt limit | J11: High | K11: Negative | L11: Seller | M11: FAIL
A12: 10 | B12: TC-LOG-010 | C12: Logistics & Delivery Management | D12: Dynamic Delivery Control | E12: Seller enables Vacation Mode | F12: Shop currently active | G12: 1. Seller toggles 'Vacation Mode' ON with date range | H12: Vacation Mode: 5 days | I12: Shop marked temporarily closed; no new orders accepted during this period; existing orders unaffected per rules | J12: High | K12: Positive | L12: Seller | M12: PASS
A13: 11 | B13: TC-LOG-011 | C13: Logistics & Delivery Management | D13: Dynamic Delivery Control | E13: Vacation Mode ends and previous settings auto-restore | F13: Vacation Mode active and end date reached | G13: 1. Wait/simulate Vacation Mode end date 2. Observe shop status | H13: Vacation Mode end date = today | I13: Shop automatically reopens with previous delivery policy settings restored | J13: Medium | K13: Positive | L13: System | M13: FAIL
A14: 12 | B14: TC-LOG-012 | C14: Logistics & Delivery Management | D14: Dynamic Delivery Control | E14: Auto-switch to Platform Logistics when seller is unavailable | F14: Seller Self Delivery unavailable; Auto-Switch enabled | G14: 1. Seller marked unavailable (e.g., no riders) 2. System checks auto-switch setting | H14: Auto-Switch = ON | I14: Order automatically routed to Platform Logistics without manual seller intervention | J14: Medium | K14: Positive | L14: System | M14: PASS
... A19: 17 | B19: TC-LOG-017 | C19: Logistics & Delivery Management | D19: Multi-Shop Logistics | E19: Seller manages independent delivery policies across multiple shops | F19: Seller owns 2+ shops with differing delivery configurations | G19: 1. Configure Shop 1 = Self Delivery only 2. Configure Shop 2 = Platform Logistics only 3. Place test orders on each | H19: Shop 1 & Shop 2 with different policies | I19: Each shop's orders follow its own independently configured logistics policy without cross-effect | J19: Medium | K19: Positive | L19: Seller | M19: PASS

Sheet Reward Engine
A1: Reward Engine (Cashback/Rewards/Coupons/Referral) — Test Case Scenarios
A2: S.No | B2: Test Case ID | C2: Module | D2: Sub-Feature / Flow | E2: Test Scenario | F2: Preconditions | G2: Test Steps | H2: Test Data | I2: Expected Result | J2: Priority | K2: Type | L2: Actor / Role | M2: Status
A3: 1 | B3: TC-RWD-001 | C3: Reward Engine (Cashback/Rewards/Coupons/Referral) | D3: Cashback | E3: Cashback credited to wallet after successful order completion | F3: Active cashback campaign eligible for the order | G3: 1. Place and complete an eligible order 2. Check wallet balance post-delivery | H3: 10% instant cashback campaign; order ₹500 | I3: ₹50 cashback credited to customer's wallet automatically after order completion | J3: High | K3: Positive | L3: System | M3: PASS
A4: 2 | B4: TC-RWD-002 | C4: Reward Engine (Cashback/Rewards/Coupons/Referral) | D4: Cashback | E4: Cashback reversed on order cancellation | F4: Cashback already credited for an order that is now cancelled | G4: 1. Complete order and receive cashback 2. Cancel/refund the order | H4: Cashback ₹50 credited, then order cancelled | I4: Cashback amount is reversed/debited from wallet per campaign reversal rules | J4: High | K4: Edge | L4: System | M4: PASS
A5: 3 | B5: TC-RWD-003 | C5: Reward Engine (Cashback/Rewards/Coupons/Referral) | D5: Cashback | E5: First-purchase cashback applied only once per customer | F5: Customer eligible for first-purchase cashback campaign | G5: 1. Place first order, receive cashback 2. Place a second order | H5: First-purchase cashback = ₹30 | I5: Cashback applied only on the first qualifying order; not repeated on subsequent orders | J5: Medium | K5: Positive | L5: System | M5: PASS
A6: 4 | B6: TC-RWD-004 | C6: Reward Engine (Cashback/Rewards/Coupons/Referral) | D6: Cashback | E6: Festival cashback campaign active only within scheduled dates | F6: Festival campaign configured with a start/end date | G6: 1. Place order within campaign window 2. Place order outside campaign window | H6: Campaign window: 1-3 Oct | I6: Cashback applied only for orders placed within the configured date range | J6: Medium | K6: Positive | L6: System | M6: PASS
A7: 5 | B7: TC-RWD-005 | C7: Reward Engine (Cashback/Rewards/Coupons/Referral) | D7: Coupons | E7: Coupon applied successfully when minimum purchase is met | F7: Coupon with minimum purchase validation configured | G7: 1. Add items worth ≥ minimum threshold to cart 2. Apply coupon at checkout | H7: Coupon: FLAT100, min purchase ₹500; cart ₹600 | I7: Coupon applied successfully; ₹100 discount reflected in final bill | J7: High | K7: Positive | L7: Customer | M7: PASS
A8: 6 | B8: TC-RWD-006 | C8: Reward Engine (Cashback/Rewards/Coupons/Referral) | D8: Coupons | E8: Coupon rejected when minimum purchase is not met | F8: Same coupon; cart below minimum threshold | G8: 1. Add items worth < minimum threshold 2. Attempt to apply coupon | H8: Cart ₹300 (below ₹500 minimum) | I8: Coupon application fails; system shows minimum-purchase-not-met message | J8: Medium | K8: Negative | L8: Customer | M8: PASS
A9: 7 | B9: TC-RWD-007 | C9: Reward Engine (Cashback/Rewards/Coupons/Referral) | D9: Coupons | E9: Coupon usage limit exceeded | F9: Coupon configured with a maximum usage count per customer | G9: 1. Use coupon up to its allowed limit 2. Attempt to use it again | H9: Coupon usage limit = 1 per customer | I9: Further application of the coupon is blocked with a usage-limit message | J9: Medium | K9: Negative | L9: Customer | M9: PASS
A10: 8 | B10: TC-RWD-008 | C10: Reward Engine (Cashback/Rewards/Coupons/Referral) | D10: Coupons | E10: Expired coupon rejected at checkout | F10: Coupon validity period has passed | G10: 1. Attempt to apply an expired coupon code at checkout | H10: Coupon expired yesterday | I10: Coupon rejected with an 'expired' message; no discount applied | J10: High | K10: Negative | L10: Customer | M10: PASS
A11: 9 | B11: TC-RWD-009 | C11: Reward Engine (Cashback/Rewards/Coupons/Referral) | D11: Referral | E11: Both referrer and referee rewarded after referee's first purchase | F11: Customer A refers Customer B via link/code; B registers and places first order | G11: 1. B registers using A's referral code 2. B places and completes first order | H11: Referral reward: ₹50 each | I11: Both A (referrer) and B (referee) receive ₹50 reward credited to their respective wallets | J11: High | K11: Positive | L11: System | M11: PASS
A12: 10 | B12: TC-RWD-010 | C12: Reward Engine (Cashback/Rewards/Coupons/Referral) | D12: Referral | E12: Duplicate referral attempt is blocked | F12: Referral already used once for a given referee account/device | G12: 1. Attempt to register the same referee again with a referral code, or reuse from a duplicate account | H12: Same referee/device attempting re-referral | I12: System blocks/flags duplicate referral; no additional reward issued | J12: High | K12: Negative | L12: System | M12: PASS
A13: 11 | B13: TC-RWD-011 | C13: Reward Engine (Cashback/Rewards/Coupons/Referral) | D13: Rewards Expiry | E13: Expired reward voucher is not usable | F13: Reward voucher past its validity/expiry date | G13: 1. Attempt to redeem an expired reward voucher at checkout | H13: Reward expired 2 days ago | I13: Redemption blocked; voucher shown as 'Expired' in Reward Center | J13: Medium | K13: Negative | L13: Customer | M13: PASS
A14: 12 | B14: TC-RWD-012 | C14: Reward Engine (Cashback/Rewards/Coupons/Referral) | D14: Funding Source | E14: Seller-sponsored cashback is deducted from seller settlement, not platform | F14: Cashback campaign configured as Seller Funded | G14: 1. Customer receives cashback from a seller-funded campaign 2. Check seller settlement impact | H14: Seller-funded cashback = ₹40 | I14: ₹40 deducted from seller's settlement amount; platform funding unaffected | J14: High | K14: Positive | L14: System | M14: PASS
... A18: 16 | B18: TC-RWD-016 | C18: Reward Engine (Cashback/Rewards/Coupons/Referral) | D18: Customer Reward Center | E18: Customer views cashback/reward/coupon history | F18: Customer has prior reward transactions | G18: 1. Open 'Reward Center' 2. Check My Cashback, My Rewards, My Coupons, My Referrals tabs | H18: Mixed history of cashback, coupons, referrals | I18: All historical and active reward data displayed accurately, categorized correctly | J18: Low | K18: Positive | L18: Customer | M18: PASS

Sheet Catalog, Search & Discovery
A1: Catalog, Search & Discovery — Test Case Scenarios
A2: S.No | B2: Test Case ID | C2: Module | D2: Sub-Feature / Flow | E2: Test Scenario | F2: Preconditions | G2: Test Steps | H2: Test Data | I2: Expected Result | J2: Priority | K2: Type | L2: Actor / Role | M2: Status
A3: 1 | B3: TC-CAT-001 | C3: Catalog, Search & Discovery | D3: Text Search | E3: Text search returns relevant products and stores | F3: Products/stores indexed in search system | G3: 1. Enter a keyword in search bar 2. Review results | H3: Search term: 'tomato' | I3: Relevant products and stores containing 'tomato' are returned, ranked by relevance | J3: Medium | K3: Positive | L3: Customer | M3: PASS
A4: 2 | B4: TC-CAT-002 | C4: Catalog, Search & Discovery | D4: Voice Search | E4: Voice search converts speech to text and returns results | F4: Microphone access granted | G4: 1. Tap voice search icon 2. Speak a product name 3. Review results | H4: Spoken query: 'milk' | I4: Speech accurately converted to text; relevant results for 'milk' displayed | J4: Medium | K4: Positive | L4: Customer | M4: PASS
A5: 3 | B5: TC-CAT-003 | C5: Catalog, Search & Discovery | D5: Category Search | E5: Search by category using grid-based browsing | F5: Categories/subcategories configured | G5: 1. Open 'Shop by Category' 2. Select a category tile 3. Drill into subcategory | H5: Category: Dairy & Eggs | I5: Correct subcategories and products under Dairy & Eggs are displayed | J5: Medium | K5: Positive | L5: Customer | M5: PASS
A6: 4 | B6: TC-CAT-004 | C6: Catalog, Search & Discovery | D6: Map Search | E6: Search store via map | F6: Store geolocation data available | G6: 1. Open map-based store discovery 2. Pan/zoom to locate nearby stores | H6: Customer location + nearby stores | I6: Stores are pinned accurately on the map based on their registered location | J6: Low | K6: Positive | L6: Customer | M6: PASS
A7: 5 | B7: TC-CAT-005 | C7: Catalog, Search & Discovery | D7: Stock Visibility | E7: Out-of-stock product excluded from search/browse results | F7: Product stock = 0 | G7: 1. Search for the out-of-stock product by name | H7: Product with 0 stock | I7: Product does not appear in search or category listing, per platform rule | J7: High | K7: Positive | L7: System | M7: PASS
A8: 6 | B8: TC-CAT-006 | C8: Catalog, Search & Discovery | D8: Time-Based Availability | E8: Time-based product/category availability enforced | F8: Product/category configured to be available only during specific hours | G8: 1. Browse the category outside its configured available hours | H8: Category available 7 AM - 11 AM only; current time = 2 PM | I8: Category/product hidden or shown as unavailable outside its configured time window | J8: Medium | K8: Edge | L8: System | M8: PASS
A9: 7 | B9: TC-CAT-007 | C9: Catalog, Search & Discovery | D9: Recommendations | E9: Add-on/cross-sell recommendation shown for a relevant product | F9: Add-on mapping configured (e.g., Umbrella + Torch) | G9: 1. View/add 'Umbrella' to cart 2. Check recommended add-ons | H9: Product: Umbrella | I9: 'Torch' or other mapped add-on product is suggested alongside | J9: Low | K9: Positive | L9: System | M9: PASS
A10: 8 | B10: TC-CAT-008 | C10: Catalog, Search & Discovery | D10: Recommendations | E10: Smart recommendation engine surfaces relevant products on home page | F10: Customer has browsing/purchase history | G10: 1. Open home page after prior purchases 2. Review 'Recommended for you' section | H10: History includes grocery purchases | I10: Home page surfaces relevant grocery-related product recommendations | J10: Low | K10: Positive | L10: System | M10: FAIL
A11: 9 | B11: TC-CAT-009 | C11: Catalog, Search & Discovery | D11: Seller Availability | E11: Alternative seller suggested when preferred seller is offline | F11: Preferred seller/store is currently offline | G11: 1. Customer visits an offline seller's shop page 2. Check for alternative suggestions | H11: Seller status = Offline | I11: System suggests nearby alternative sellers offering similar products | J11: Medium | K11: Edge | L11: System | M11: PASS
A12: 10 | B12: TC-CAT-010 | C12: Catalog, Search & Discovery | D12: Homepage CMS | E12: Homepage banners/sections update dynamically per admin configuration | F12: Admin updates homepage banners/categories/featured products | G12: 1. Admin changes a banner/featured product in CMS 2. Refresh customer home page | H12: New banner uploaded by admin | I12: Updated banner/section reflects on customer app home page without requiring an app update | J12: Medium | K12: Positive | L12: Admin | M12: PASS

Sheet Notifications & Post-Order
A1: Notifications & Post-Order Engagement — Test Case Scenarios
A2: S.No | B2: Test Case ID | C2: Module | D2: Sub-Feature / Flow | E2: Test Scenario | F2: Preconditions | G2: Test Steps | H2: Test Data | I2: Expected Result | J2: Priority | K2: Type | L2: Actor / Role | M2: Status
A3: 1 | B3: TC-NOT-001 | C3: Notifications & Post-Order Engagement | D3: Customer Notifications | E3: Customer receives notification for each order status change | F3: Notifications enabled | G3: 1. Place an order and progress it through the full lifecycle 2. Track notifications received | H3: Full lifecycle: Placed -> Accepted -> Packed -> Out for Delivery -> Delivered | I3: A distinct, correctly-timed notification is received for every status transition | J3: High | K3: Positive | L3: Customer | M3: PASS
A4: 2 | B4: TC-NOT-002 | C4: Notifications & Post-Order Engagement | D4: Seller Notifications | E4: Seller receives notification of new scheduled order and cut-off reminder | F4: Scheduled order placed for seller's shop | G4: 1. Customer places a scheduled order 2. Observe seller notifications as cut-off approaches | H4: Scheduled order, cut-off reminder configured 1 hr before | I4: Seller notified immediately of the new scheduled order, and again as a cut-off reminder | J4: Medium | K4: Positive | L4: Seller | M4: FAIL
A5: 3 | B5: TC-NOT-003 | C5: Notifications & Post-Order Engagement | D5: Assistant Notifications | E5: Assistant receives notification of an assigned order/task | F5: Assistant assigned to a shop with incoming order | G5: 1. New order arrives at assistant's assigned shop 2. Check assistant notifications | H5: Assistant assigned to Shop 1 | I5: Assistant receives a task/order notification for Shop 1 only | J5: Medium | K5: Positive | L5: Assistant | M5: PASS
A6: 4 | B6: TC-NOT-004 | C6: Notifications & Post-Order Engagement | D6: Super Admin Notifications | E6: Super Admin receives escalation notification for a pending refund approval | F6: A refund approval is pending beyond SLA | G6: 1. Refund request remains pending past threshold time 2. Check Super Admin notifications | H6: Refund pending > 24 hrs | I6: Super Admin receives an escalation alert requiring action | J6: Medium | K6: Positive | L6: Super Admin | M6: PASS
A7: 5 | B7: TC-NOT-005 | C7: Notifications & Post-Order Engagement | D7: Refund Window | E7: Refund/complaint option available within 24-hour post-delivery window | F7: Order delivered less than 24 hours ago | G7: 1. Open a recently delivered order (within 24 hrs) 2. Check for Refund/Complaint option and countdown timer | H7: Delivered 5 hours ago | I7: Refund/Complaint option visible with a live countdown ('Available for 19h 0m') | J7: High | K7: Positive | L7: Customer | M7: PASS
A8: 6 | B8: TC-NOT-006 | C8: Notifications & Post-Order Engagement | D8: Refund Window | E8: Refund/complaint option unavailable after 24-hour window expires | F8: Order delivered more than 24 hours ago | G8: 1. Open an order delivered 30 hours ago 2. Check for Refund/Complaint option | H8: Delivered 30 hours ago | I8: Refund/Complaint option is disabled/hidden; window has expired | J8: High | K8: Negative | L8: Customer | M8: PASS
A9: 7 | B9: TC-NOT-007 | C9: Notifications & Post-Order Engagement | D9: Category-Based Refund | E9: Category-based refund restriction blocks a refund request | F9: Admin has disabled refunds for a specific product category | G9: 1. Attempt to raise a refund for a product in a refund-disabled category | H9: Category: perishable goods, refunds disabled | I9: Refund request rejected with a category-restriction message | J9: Medium | K9: Negative | L9: Customer | M9: PASS
A10: 8 | B10: TC-NOT-008 | C10: Notifications & Post-Order Engagement | D10: Feedback & Rating | E10: Customer submits feedback/rating after delivery | F10: Order delivered | G10: 1. Open delivered order 2. Submit a star rating and written feedback | H10: Rating: 5 stars + comment | I10: Feedback saved and reflected on the seller/product's rating aggregate | J10: Low | K10: Positive | L10: Customer | M10: PASS
A11: 9 | B11: TC-NOT-009 | C11: Notifications & Post-Order Engagement | D11: Reorder | E11: Customer reorders a previous order successfully | F11: Delivered order exists in history; items still in stock | G11: 1. Open order history 2. Tap 'Reorder' on a past order | H11: Past order with 3 in-stock items | I11: New cart pre-populated with the same items at current pricing; customer can checkout | J11: Low | K11: Positive | L11: Customer | M11: PASS
A12: 10 | B12: TC-NOT-010 | C12: Notifications & Post-Order Engagement | D12: Favourites | E12: Customer adds a seller/store to favourites | F12: Customer viewing a store page | G12: 1. Open store page 2. Tap 'Follow'/'Add to Favourites' | H12: Any active store | I12: Store added to customer's favourites list; appears in 'My Favourites' for quick access | J12: Low | K12: Positive | L12: Customer | M12: PASS

Sheet E2E Business Flow
A1: End-to-End Business Flow Testing — Test Case Scenarios
A2: S.No | B2: Test Case ID | C2: Module | D2: Sub-Feature / Flow | E2: Test Scenario | F2: Preconditions | G2: Test Steps | H2: Test Data | I2: Expected Result | J2: Priority | K2: Type | L2: Actor / Role | M2: Status
A3: 1 | B3: TC-E2E-001 | C3: End-to-End Business Flow Testing | D3: Customer Journey | E3: Full customer journey: browse to delivered & rated | F3: Customer registered; shop active with in-stock products | G3: 1. Browse shop, add items to cart 2. Place order & pay 3. Track through Accepted->Packed->Out for Delivery->Delivered 4. Submit rating/feedback | H3: Standard multi-item cart | I3: Every stage completes without manual intervention; final state = 'Completed' with rating recorded | J3: High | K3: Positive | L3: Customer | M3: PASS
A4: 2 | B4: TC-E2E-002 | C4: End-to-End Business Flow Testing | D4: Seller Journey | E4: Full seller journey: onboarding to first settlement | F4: New seller with no prior activity | G4: 1. Register, complete KYC, subscribe/choose commission 2. Create shop & add products 3. Accept and fulfill an order 4. View settlement report | H4: New seller end-to-end | I4: Seller successfully onboards, sells, and receives an accurate settlement reflecting commission/subscription rules | J4: High | K4: Positive | L4: Seller | M4: PASS
A5: 3 | B5: TC-E2E-003 | C5: End-to-End Business Flow Testing | D5: Assistant Journey | E5: Assistant handles a full order within granted permissions | F5: Assistant assigned to a shop with Operational role | G5: 1. Assistant logs in 2. Accepts order, updates stock, packs, contacts customer 3. Attempts a finance action (should fail) | H5: Operational-role assistant | I5: All allowed order actions succeed; finance action correctly blocked; seller retains full oversight | J5: High | K5: Positive | L5: Assistant | M5: PASS
A6: 4 | B6: TC-E2E-004 | C6: End-to-End Business Flow Testing | D6: Delivery Partner Journey | E6: Full delivery partner journey: assignment to confirmation | F6: Order accepted and packed; Platform Logistics enabled | G6: 1. Delivery partner receives assignment 2. Navigates to seller, collects order 3. Delivers to customer, verifies via OTP/QR 4. Marks delivery complete | H6: Platform-logistics order | I6: Delivery partner completes full flow; order marked 'Delivered'; all parties notified | J6: High | K6: Positive | L6: Delivery Partner | M6: PASS
A7: 5 | B7: TC-E2E-005 | C7: End-to-End Business Flow Testing | D7: Super Admin Journey | E7: Super Admin end-to-end oversight of a disputed order | F7: Order has an escalated cancellation/refund dispute | G7: 1. Super Admin reviews escalation 2. Overrides seller decision or approves refund 3. Confirms settlement adjustment | H7: Disputed order case | I7: Dispute resolved with correct financial adjustment; full audit trail captured | J7: High | K7: Positive | L7: Super Admin | M7: PASS
A8: 6 | B8: TC-E2E-006 | C8: End-to-End Business Flow Testing | D8: Operator Journey | E8: Operator performs day-to-day operational monitoring across shops | F8: Operator role defined with cross-shop operational visibility (non-financial) | G8: 1. Operator logs in 2. Monitors live orders/escalations across multiple shops 3. Reassigns/nudges a stuck order 4. Attempts to access settlement data | H8: Operator account, multi-shop visibility | I8: Operator can monitor and action operational issues; financial/settlement data remains inaccessible | J8: High | K8: Positive | L8: Operator | M8: PASS
A9: 7 | B9: TC-E2E-007 | C9: End-to-End Business Flow Testing | D9: Finance/Tax Team Journey | E9: Finance/Tax team reconciles settlements and generates tax reports | F9: Completed orders with GST and commission data across multiple sellers | G9: 1. Finance user logs in 2. Opens Settlement & GST reports 3. Filters by date/seller/city 4. Exports report | H9: Multi-seller settlement data, current tax period | I9: Finance/Tax team can view, filter, and export accurate settlement and GST data; no access to unrelated operational controls (e.g., product editing) | J9: High | K9: Positive | L9: Finance/Tax Team | M9: FAIL
A10: 8 | B10: TC-E2E-008 | C10: End-to-End Business Flow Testing | D10: Cross-Role Handoff | E10: Order flows correctly across all roles end-to-end (Customer->Seller->Delivery->Finance) | F10: Fresh order placed under Platform Logistics with commission model | G10: 1. Customer places order 2. Seller accepts & packs 3. Delivery partner delivers 4. Finance team sees settlement reflect the completed order | H10: Full role chain scenario | I10: Each role's action correctly triggers the next stage; final settlement matches order value minus commission/charges | J10: High | K10: Positive | L10: All Roles | M10: PASS
A11: 9 | B11: TC-E2E-009 | C11: End-to-End Business Flow Testing | D11: Cross-Role Handoff | E11: Partial cancellation propagates correctly across seller, customer wallet, and finance settlement | F11: Multi-item order; one item unavailable | G11: 1. Seller partially cancels unavailable item 2. Customer wallet is refunded 3. Finance team's settlement reflects the adjustment | H11: 1 of 3 items cancelled, value ₹80 | I11: Wallet refund, revised invoice, and settlement all reconcile to the same ₹80 adjustment across roles | J11: High | K11: Positive | L11: All Roles | M11: PASS
A12: 10 | B12: TC-E2E-010 | C12: End-to-End Business Flow Testing | D12: Mixed Order Type Flow | E12: Business flow for a mixed regular + pre-order cart end-to-end | F12: Cart contains a regular item and a pre-order item | G12: 1. Place mixed cart order 2. Seller processes as scheduled order 3. Deliver on pre-order date 4. Confirm settlement timing | H12: Mixed cart, pre-order date T+15 | I12: Entire order fulfilled on the pre-order date; settlement triggered only after delivery per business rule | J12: Medium | K12: Positive | L12: All Roles | M12: PASS
A13: 11 | B13: TC-E2E-011 | C13: End-to-End Business Flow Testing | D13: Subscription Expiry Mid-Flow | E13: Seller subscription expires while an order is in progress | F13: Active order in 'Preparing' state; seller subscription expires before delivery | G13: 1. Let subscription lapse while order is mid-fulfillment 2. Continue order to delivery | H13: Subscription expiry during active order | I13: Existing order is still fulfilled normally per business rule; only new orders/listings are blocked going forward | J13: High | K13: Edge | L13: Seller/System | M13: PASS
A14: 12 | B14: TC-E2E-012 | C14: End-to-End Business Flow Testing | D14: Logistics Failure Handoff | E14: Business flow when assigned delivery partner is unavailable | F14: Platform Logistics order ready for assignment; no delivery partner available in area | G14: 1. Seller completes packing 2. System attempts logistics assignment 3. No partner available | H14: Zero available delivery partners | I14: Order flagged for manual reassignment/escalation to Operator or Super Admin; customer kept informed | J14: Medium | K14: Edge | L14: Operator/Super Admin | M14: PASS
A15: 13 | B15: TC-E2E-013 | C15: End-to-End Business Flow Testing | D15: Reward-to-Settlement Flow | E15: Seller-funded cashback correctly flows into final settlement | F15: Order completed under a seller-funded cashback campaign | G15: 1. Customer receives seller-funded cashback 2. Finance team reviews seller's settlement | H15: Seller-funded cashback ₹40 on ₹500 order | I15: Settlement report shows cashback deduction alongside commission, correctly reducing seller payout | J15: Medium | K15: Positive | L15: Finance/Tax Team | M15: PASS

Sheet Role-wise Testing (New Roles)
A1: Role-wise Testing — Delivery Partner, Operator, Finance/Tax — Test Case Scenarios
A2: S.No | B2: Test Case ID | C2: Module | D2: Sub-Feature / Flow | E2: Test Scenario | F2: Preconditions | G2: Test Steps | H2: Test Data | I2: Expected Result | J2: Priority | K2: Type | L2: Actor / Role | M2: Status
A3: 1 | B3: TC-ROLE2-001 | C3: Role-wise Testing — Delivery Partner, Operator, Finance/Tax | D3: Delivery Partner Access | E3: Delivery partner can view only assigned delivery requests | F3: Delivery partner logged in with active assignments | G3: 1. Delivery partner opens app 2. Views assigned deliveries list | H3: 2 active assignments out of 50 platform-wide orders | I3: Only the 2 assigned deliveries are visible; no access to unrelated orders or seller/customer financial data | J3: High | K3: Positive | L3: Delivery Partner | M3: PASS
A4: 2 | B4: TC-ROLE2-002 | C4: Role-wise Testing — Delivery Partner, Operator, Finance/Tax | D4: Delivery Partner Access | E4: Delivery partner attempts to access customer payment details | F4: Delivery partner viewing an assigned order | G4: 1. Delivery partner opens assigned order details 2. Looks for payment/financial information | H4: Assigned order with online payment | I4: Payment details are not exposed to delivery partner; only address/contact needed for delivery is visible | J4: High | K4: Negative | L4: Delivery Partner | M4: PASS
A5: 3 | B5: TC-ROLE2-003 | C5: Role-wise Testing — Delivery Partner, Operator, Finance/Tax | D5: Delivery Partner Access | E5: Delivery partner reports a delivery exception and updates status | F5: Order out for delivery | G5: 1. Delivery partner marks 'Customer Unreachable' 2. Adds a note 3. Submits | H5: Delivery exception scenario | I5: Status updates correctly; seller/customer/Operator notified; exception logged for follow-up | J5: Medium | K5: Positive | L5: Delivery Partner | M5: PASS
A6: 4 | B6: TC-ROLE2-004 | C6: Role-wise Testing — Delivery Partner, Operator, Finance/Tax | D6: Operator Access | E6: Operator has cross-shop operational visibility without financial access | F6: Operator role configured | G6: 1. Operator logs in 2. Views orders/escalations across multiple shops 3. Attempts to view seller payout/settlement figures | H6: Operator with multi-shop scope | I6: Order/escalation data visible across shops; settlement/payout figures remain inaccessible | J6: High | K6: Positive | L6: Operator | M6: PASS
A7: 5 | B7: TC-ROLE2-005 | C7: Role-wise Testing — Delivery Partner, Operator, Finance/Tax | D7: Operator Access | E7: Operator reassigns a stuck/escalated order | F7: Order stuck beyond SLA (e.g., unaccepted for too long) | G7: 1. Operator identifies stuck order in queue 2. Reassigns/nudges seller or escalates to Super Admin | H7: Order unaccepted for 45+ minutes | I7: Action taken and logged; order progresses or is correctly escalated further | J7: Medium | K7: Positive | L7: Operator | M7: PASS
A8: 6 | B8: TC-ROLE2-006 | C8: Role-wise Testing — Delivery Partner, Operator, Finance/Tax | D8: Operator Access | E8: Operator attempts to modify commission/subscription configuration | F8: Operator role active | G8: 1. Operator navigates to Commission/Subscription settings 2. Attempts to edit a rule | H8: Any commission rule | I8: Access blocked; only Super Admin can configure commission/subscription rules | J8: High | K8: Negative | L8: Operator | M8: PASS
A9: 7 | B9: TC-ROLE2-007 | C9: Role-wise Testing — Delivery Partner, Operator, Finance/Tax | D9: Finance/Tax Access | E9: Finance/Tax team can view and export GST invoices and settlement reports | F9: Finance role configured with reporting access | G9: 1. Finance user opens Settlement/GST module 2. Filters by date range and seller 3. Exports to Excel/PDF | H9: Multi-seller data, current quarter | I9: Accurate report generated and exportable; figures match individual order/settlement records | J9: High | K9: Positive | L9: Finance/Tax Team | M9: FAIL
A10: 8 | B10: TC-ROLE2-008 | C10: Role-wise Testing — Delivery Partner, Operator, Finance/Tax | D10: Finance/Tax Access | E10: Finance/Tax team attempts to edit product listings or accept orders | F10: Finance role active | G10: 1. Finance user attempts to navigate to Product Management or Order Acceptance screens | H10: Any product/order | I10: Access blocked; Finance/Tax role is restricted to financial/tax data only, no operational control | J10: High | K10: Negative | L10: Finance/Tax Team | M10: PASS
A11: 9 | B11: TC-ROLE2-009 | C11: Role-wise Testing — Delivery Partner, Operator, Finance/Tax | D11: Finance/Tax Access | E11: Finance/Tax team reconciles a held settlement after dispute resolution | F11: Previously held settlement now cleared by Super Admin | G11: 1. Finance user opens settlement queue 2. Confirms status changed from 'On Hold' to 'Settled' 3. Verifies final payable amount | H11: Resolved dispute case | I11: Settlement figure matches post-resolution calculation; reconciliation recorded correctly | J11: Medium | K11: Positive | L11: Finance/Tax Team | M11: PASS
A12: 10 | B12: TC-ROLE2-010 | C12: Role-wise Testing — Delivery Partner, Operator, Finance/Tax | D12: Cross-Role Data Isolation | E12: Delivery Partner, Operator, and Finance/Tax roles cannot access each other's restricted modules | F12: All three roles provisioned with their intended scopes | G12: 1. Log in as each role in turn 2. Attempt to access modules outside intended scope (e.g., Delivery Partner -> Settlement; Finance -> Delivery assignment) | H12: Three distinct role logins | I12: Each role is confined strictly to its intended module set; no cross-role data leakage occurs | J12: High | K12: Edge | L12: Delivery Partner/Operator/Finance | M12: PASS
A13: 11 | B13: TC-ROLE2-011 | C13: Role-wise Testing — Delivery Partner, Operator, Finance/Tax | D13: Role Escalation Path | E13: Escalation correctly routes: Assistant -> Seller -> Operator -> Super Admin | F13: Issue unresolved at Assistant level | G13: 1. Assistant cannot resolve an issue (e.g., permission-restricted) 2. Escalates to Seller 3. Seller escalates to Operator/Super Admin if unresolved | H13: Multi-level escalation scenario | I13: Escalation path followed correctly with each role's action logged; issue reaches the correct authority level | J13: Medium | K13: Positive | L13: All Roles | M13: FAIL

Sheet Integration Testing
A1: Integration Testing (Cross-Module) — Test Case Scenarios
A2: S.No | B2: Test Case ID | C2: Module | D2: Sub-Feature / Flow | E2: Test Scenario | F2: Preconditions | G2: Test Steps | H2: Test Data | I2: Expected Result | J2: Priority | K2: Type | L2: Actor / Role | M2: Status
A3: 1 | B3: TC-INT-001 | C3: Integration Testing (Cross-Module) | D3: Orders <-> Payments | E3: Order confirmation only after payment gateway success | F3: Payment gateway integrated | G3: 1. Place order 2. Complete payment via gateway 3. Verify order status change | H3: Successful payment transaction | I3: Order status moves to 'Placed/Confirmed' only after payment gateway confirms success; failed payment leaves order unconfirmed | J3: High | K3: Positive | L3: System | M3: PASS
A4: 2 | B4: TC-INT-002 | C4: Integration Testing (Cross-Module) | D4: Orders <-> Products/Inventory | E4: Stock is decremented correctly when an order is placed/accepted | F4: Product with known stock count | G4: 1. Note current stock 2. Place and accept an order for that product 3. Recheck stock | H4: Initial stock = 20; order qty = 3 | I4: Stock reduces to 17 immediately/at the correct configured stage (placement or acceptance) | J4: High | K4: Positive | L4: System | M4: PASS
A5: 3 | B5: TC-INT-003 | C5: Integration Testing (Cross-Module) | D5: Orders <-> Logistics | E5: Logistics assignment triggers only after seller packs the order | F5: Platform Logistics enabled for shop | G5: 1. Seller accepts and packs order 2. Observe logistics assignment trigger | H5: Standard platform-logistics order | I5: Delivery partner assignment occurs only post-packing, not earlier | J5: High | K5: Positive | L5: System | M5: FAIL
A6: 4 | B6: TC-INT-004 | C6: Integration Testing (Cross-Module) | D6: Orders <-> Wallet | E6: Cancellation refund correctly credits customer wallet in real time | F6: Order eligible for wallet refund on cancellation | G6: 1. Cancel an order/item eligible for refund 2. Check wallet balance immediately after | H6: Order value ₹200 | I6: Wallet balance increases by exactly ₹200 immediately after cancellation is processed | J6: High | K6: Positive | L6: System | M6: PASS
A7: 5 | B7: TC-INT-005 | C7: Integration Testing (Cross-Module) | D7: Orders <-> Rewards | E7: Cashback/reward calculation reflects correct order value after partial cancellation | F7: Order with active cashback campaign; partial cancellation occurs before completion | G7: 1. Place order eligible for 10% cashback 2. Partially cancel one item 3. Complete remaining order 4. Check cashback credited | H7: Original ₹500 order, ₹100 item cancelled | I7: Cashback calculated on the final ₹400 order value, not the original ₹500 | J7: High | K7: Positive | L7: System | M7: PASS
A8: 6 | B8: TC-INT-006 | C8: Integration Testing (Cross-Module) | D8: Orders <-> Notifications | E8: Every module event triggers the correct role-specific notification | F8: Notification service integrated across modules | G8: 1. Trigger events from Orders, Payments, Logistics, Rewards modules in sequence 2. Check notification log per role | H8: Full lifecycle event chain | I8: Each module's event produces the correct notification to the correct role without duplication or omission | J8: Medium | K8: Positive | L8: System | M8: BLOCKED
A9: 7 | B9: TC-INT-007 | C9: Integration Testing (Cross-Module) | D9: Subscriptions <-> Shop Visibility | E9: Shop/product visibility toggles correctly with subscription state changes | F9: Seller subscription active | G9: 1. Let subscription expire 2. Check shop/product visibility on customer app 3. Renew subscription 4. Recheck visibility | H9: Subscription expiry then renewal | I9: Shop/products hide immediately on expiry and reappear immediately on renewal, consistent across all customer-facing views | J9: High | K9: Positive | L9: System | M9: PASS
A10: 8 | B10: TC-INT-008 | C10: Integration Testing (Cross-Module) | D10: Settlement <-> Commission/Subscription | E10: Settlement correctly applies the seller's active commission or subscription model | F10: Seller on Commission Model for some orders, Subscription Model for others (if seller changed model) | G10: 1. Complete an order while on Commission Model 2. Switch seller to Subscription Model 3. Complete another order 4. Compare settlements | H10: Two orders under different business models | I10: First order settlement includes commission deduction; second order settlement has no commission deduction (rental-based) | J10: High | K10: Positive | L10: System | M10: PASS
A11: 9 | B11: TC-INT-009 | C11: Integration Testing (Cross-Module) | D11: Settlement <-> Refunds | E11: Refund on a delivered order correctly reduces/reverses seller settlement | F11: Delivered order later refunded within allowed window | G11: 1. Complete order and initial settlement calculation 2. Process a post-delivery refund 3. Recheck settlement | H11: ₹150 refund on a ₹600 order | I11: Settlement adjusts to reflect the ₹150 deduction; commission on refunded amount is also reversed | J11: High | K11: Positive | L11: System | M11: PASS
A12: 10 | B12: TC-INT-010 | C12: Integration Testing (Cross-Module) | D12: Coupons <-> Pricing/Invoice | E12: Applied coupon discount reflects correctly in final invoice and seller settlement | F12: Platform-funded coupon applied at checkout | G12: 1. Apply a ₹50 platform-funded coupon 2. Complete order 3. Check invoice and seller settlement | H12: Order ₹500, coupon ₹50 (platform funded) | I12: Customer invoice shows ₹450 payable; seller settlement is unaffected (platform absorbs the ₹50) | J12: Medium | K12: Positive | L12: System | M12: PASS
A13: 11 | B13: TC-INT-011 | C13: Integration Testing (Cross-Module) | D13: Search <-> Inventory | E13: Search index updates in near real-time when stock changes | F13: Product goes out of stock | G13: 1. Product stock reaches 0 2. Immediately search for the product | H13: Stock transition 1 -> 0 | I13: Product disappears from search/browse results within the expected sync window | J13: Medium | K13: Positive | L13: System | M13: PASS
A14: 12 | B14: TC-INT-012 | C14: Integration Testing (Cross-Module) | D14: Referral <-> Wallet/Settlement | E14: Referral reward correctly flows into wallet and, if seller-funded, into settlement | F14: Seller referral campaign; new seller completes subscription purchase | G14: 1. Referral triggers after subscription purchase 2. Check referrer's reward destination | H14: Seller referral reward ₹500 | I14: Reward credited to correct wallet/account; if platform-funded, no seller settlement impact; if seller-funded, settlement reflects deduction | J14: Medium | K14: Positive | L14: System | M14: PASS

Sheet Exception & Negative Testing
A1: Exception & Negative Testing — Test Case Scenarios
A2: S.No | B2: Test Case ID | C2: Module | D2: Sub-Feature / Flow | E2: Test Scenario | F2: Preconditions | G2: Test Steps | H2: Test Data | I2: Expected Result | J2: Priority | K2: Type | L2: Actor / Role | M2: Status
A3: 1 | B3: TC-EXC-001 | C3: Exception & Negative Testing | D3: Invalid Input | E3: Checkout blocked with invalid/incomplete address | F3: Customer at checkout | G3: 1. Leave mandatory address fields blank or enter invalid pincode 2. Attempt to place order | H3: Blank city field / invalid pincode format | I3: Order placement blocked with clear validation message; no order record created | J3: High | K3: Negative | L3: System | M3: PASS
A4: 2 | B4: TC-EXC-002 | C4: Exception & Negative Testing | D4: Invalid Input | E4: Coupon field rejects a non-existent coupon code | F4: Checkout screen | G4: 1. Enter a random/invalid coupon code 2. Apply | H4: Coupon code: 'XXXXNOTEXIST' | I4: System shows 'Invalid coupon code'; no discount applied | J4: Medium | K4: Negative | L4: System | M4: PASS
A5: 3 | B5: TC-EXC-003 | C5: Exception & Negative Testing | D5: Payment Failure | E5: Order remains unconfirmed when payment gateway declines transaction | F5: Payment attempted with insufficient funds/declined card | G5: 1. Attempt payment with a card configured to decline 2. Observe order status | H5: Simulated payment decline | I5: Order stays in 'Payment Pending/Failed' state; no stock deduction or seller notification occurs | J5: High | K5: Negative | L5: System | M5: PASS
A6: 4 | B6: TC-EXC-004 | C6: Exception & Negative Testing | D6: Payment Failure | E6: Auto-cancel after payment timeout | F6: Customer initiates payment but abandons/times out | G6: 1. Start payment 2. Do not complete within the configured timeout window | H6: Payment timeout = 10 minutes | I6: Order auto-cancels after timeout; reserved stock (if any) is released | J6: Medium | K6: Edge | L6: System | M6: PASS
A7: 5 | B7: TC-EXC-005 | C7: Exception & Negative Testing | D7: Stock Shortage | E7: Seller goes out of stock on an item after order placed but before acceptance | F7: Item in stock at order time; goes to 0 before seller reviews | G7: 1. Place order 2. Seller marks item out of stock before accepting 3. Seller reviews order | H7: Race-condition stock scenario | I7: Seller is prompted into Partial Order Decision flow (cancel/replace/split) rather than a silent failure | J7: High | K7: Edge | L7: System | M7: FAIL
A8: 6 | B8: TC-EXC-006 | C8: Exception & Negative Testing | D8: Stock Shortage | E8: Seller goes out of stock before a scheduled delivery date arrives | F8: Scheduled order accepted; item goes out of stock before the scheduled date | G8: 1. Accept scheduled order 2. Item stock hits 0 before scheduled delivery date 3. Seller reviews order near delivery date | H8: Scheduled order, stock depleted mid-way | I8: Seller notified in time to trigger replacement/partial cancellation before the scheduled date, avoiding a failed delivery | J8: High | K8: Edge | L8: Seller/System | M8: PASS
A9: 7 | B9: TC-EXC-007 | C9: Exception & Negative Testing | D9: Cancellation Edge Case | E9: Cancellation request submitted at the exact moment logistics is assigned | F9: Cancellation request and logistics assignment occur near-simultaneously | G9: 1. Customer submits cancellation request 2. Logistics assignment completes at nearly the same time | H9: Race condition between two events | I9: System resolves deterministically per business rule (logistics-assignment lock takes precedence, or request queued) without corrupting order state | J9: Medium | K9: Edge | L9: System | M9: PASS
A10: 8 | B10: TC-EXC-008 | C10: Exception & Negative Testing | D10: Refund Edge Case | E10: Refund requested exactly at the 24-hour boundary | F10: Order delivered exactly 24 hours ago | G10: 1. Attempt to raise a refund/complaint at the exact 24-hour mark | H10: Delivery timestamp + 24h00m | I10: System applies the configured boundary rule consistently (inclusive/exclusive as designed) without ambiguity | J10: Medium | K10: Edge | L10: System | M10: PASS
A11: 9 | B11: TC-EXC-009 | C11: Exception & Negative Testing | D11: Subscription Expiry Edge Case | E11: Order placed in the final minute before seller subscription expires | F11: Seller subscription expiring within the next 1 minute | G11: 1. Customer places order just before expiry 2. Subscription expires 3. Seller attempts to accept | H11: Subscription expiry at 11:59:59 PM | I11: Order placed before expiry is still valid and can be accepted/fulfilled; only new orders after expiry are blocked | J11: Medium | K11: Edge | L11: System | M11: FAIL
A12: 10 | B12: TC-EXC-010 | C12: Exception & Negative Testing | D12: Permission Violation | E12: Assistant attempts an action after Seller has just revoked their access | F12: Seller disables assistant access mid-session | G12: 1. Assistant is logged in and mid-action 2. Seller revokes assistant access 3. Assistant attempts to submit the action | H12: Access revoked mid-session | I12: Action is rejected immediately; assistant is logged out or shown 'Access Revoked' on next action | J12: High | K12: Negative | L12: Assistant | M12: PASS
A13: 11 | B13: TC-EXC-011 | C13: Exception & Negative Testing | D13: Permission Violation | E13: Expired/invalid session token used to call a protected API | F13: Session token expired | G13: 1. Use an expired auth token to call an order/finance API endpoint | H13: Expired JWT/session token | I13: API rejects request with an authentication error; no data returned or modified | J13: High | K13: Negative | L13: System | M13: PASS
A14: 12 | B14: TC-EXC-012 | C14: Exception & Negative Testing | D14: Error Handling | E14: System behavior when logistics partner API/service is down | F14: Platform Logistics assignment step; logistics service unavailable | G14: 1. Trigger logistics assignment while the logistics service is simulated as down | H14: Logistics API down | I14: Order is queued/flagged for retry or manual assignment; customer is informed of a delay rather than the app crashing | J14: High | K14: Edge | L14: System | M14: PASS
... A16: 14 | B16: TC-EXC-014 | C16: Exception & Negative Testing | D16: Wallet Edge Case | E16: Refund attempted on an order with an already-closed/deleted customer account | F16: Customer account deactivated after order completion | G16: 1. Order delivered 2. Customer account deactivated 3. Refund/cancellation triggered on that order | H16: Deactivated customer account | I16: System handles gracefully — refund routed per policy (e.g., held for manual review) rather than failing silently | J16: Medium | K16: Edge | L16: System | M16: FAIL

Sheet SEO & Discoverability
A1: SEO & Google Discoverability Testing — Test Case Scenarios
A2: S.No | B2: Test Case ID | C2: Module | D2: Sub-Feature / Flow | E2: Test Scenario | F2: Preconditions | G2: Test Steps | H2: Test Data | I2: Expected Result | J2: Priority | K2: Type | L2: Actor / Role | M2: Status
A3: 1 | B3: TC-SEO-001 | C3: SEO & Google Discoverability Testing | D3: URL Structure | E3: Shop, product, and category pages use SEO-friendly URLs | F3: Public web pages available for shops/products/categories | G3: 1. Open a shop page, a product page, and a category page 2. Inspect the URL structure | H3: e.g., /shop/fresh-mart-koramangala, /product/amul-fresh-milk-1l | I3: URLs are human-readable, use slugs (not raw IDs only), and follow a consistent, crawlable pattern | J3: High | K3: Positive | L3: System | M3: PASS
A4: 2 | B4: TC-SEO-002 | C4: SEO & Google Discoverability Testing | D4: Meta Tags | E4: Meta title and description are correctly generated per page | F4: Shop/product/category pages live | G4: 1. Inspect page source of a product page 2. Check <title> and meta description tags | H4: Product: 'Amul Fresh Milk 1L' | I4: Unique, descriptive title and meta description generated per page, incorporating product/shop name and relevant keywords | J4: High | K4: Positive | L4: System | M4: PASS
A5: 3 | B5: TC-SEO-003 | C5: SEO & Google Discoverability Testing | D5: Schema Markup | E5: Structured data (schema.org) present for products and stores | F5: Product/store pages live | G5: 1. Run a rich-results/structured-data test on a product and a store page | H5: Product page with price, availability, rating | I5: Valid Product/LocalBusiness schema markup detected with no critical errors | J5: High | K5: Positive | L5: System | M5: PASS
A6: 4 | B6: TC-SEO-004 | C6: SEO & Google Discoverability Testing | D6: XML Sitemap | E6: XML sitemap is generated and includes all key page types | F6: Sitemap endpoint configured | G6: 1. Fetch /sitemap.xml 2. Verify inclusion of shop, product, category, and offer URLs | H6: Sitemap covering all active listings | I6: Sitemap is valid XML, lists current active pages, and updates as new shops/products are added | J6: High | K6: Positive | L6: System | M6: PASS
A7: 5 | B7: TC-SEO-005 | C7: SEO & Google Discoverability Testing | D7: Robots.txt | E7: robots.txt correctly allows/disallows the intended paths | F7: robots.txt deployed | G7: 1. Fetch /robots.txt 2. Verify allowed/disallowed paths and sitemap reference | H7: Standard robots.txt | I7: Public shop/product/category pages are crawlable; admin/checkout/account paths are disallowed; sitemap URL is referenced | J7: Medium | K7: Positive | L7: System | M7: PASS
A8: 6 | B8: TC-SEO-006 | C8: SEO & Google Discoverability Testing | D8: Auto-Indexing | E8: Newly published shop/product/category/offer pages are discoverable for indexing | F8: New shop or product published | G8: 1. Publish a new product/shop 2. Verify it is added to sitemap and is crawlable | H8: Newly onboarded seller with new product | I8: New page appears in sitemap and is fetchable/crawlable without manual intervention | J8: Medium | K8: Positive | L8: System | M8: PASS
A9: 7 | B9: TC-SEO-007 | C9: SEO & Google Discoverability Testing | D9: Local SEO | E9: Location-based pages/search support Area, City, Pincode and 'Near Me' queries | F9: Multiple shops across different areas/cities configured | G9: 1. Search '<category> near me' 2. Search '<category> in <city/pincode>' | H9: e.g., 'grocery near me', 'grocery in Koramangala 560034' | I9: Relevant local results returned; location-based landing pages (if any) are indexable and correctly targeted | J9: High | K9: Positive | L9: System | M9: PASS
A10: 8 | B10: TC-SEO-008 | C10: SEO & Google Discoverability Testing | D10: Search Console Readiness | E10: Site is verified and readable in Google Search Console | F10: Search Console property set up | G10: 1. Verify domain ownership in Search Console 2. Submit sitemap 3. Check for crawl errors | H10: Production domain | I10: Site verified successfully; sitemap submitted without errors; no critical crawl/indexing errors reported | J10: High | K10: Positive | L10: System | M10: BLOCKED
A11: 9 | B11: TC-SEO-009 | C11: SEO & Google Discoverability Testing | D11: Core Web Vitals | E11: Core Web Vitals meet Google's recommended thresholds | F11: Key pages (home, product, category) available for testing | G11: 1. Run PageSpeed Insights / Lighthouse on home, product, and category pages 2. Review LCP, CLS, INP scores | H11: Mobile and desktop tests | I11: LCP < 2.5s, CLS < 0.1, INP within 'Good' threshold on mobile and desktop for key pages | J11: High | K11: Positive | L11: System | M11: BLOCKED
A12: 10 | B12: TC-SEO-010 | C12: SEO & Google Discoverability Testing | D12: Mobile Friendliness | E12: Pages pass Google's Mobile-Friendly Test | F12: Public pages accessible | G12: 1. Run Mobile-Friendly Test on home, shop, and product pages | H12: Mobile viewport test | I12: All tested pages pass with no mobile-usability issues (text size, tap targets, viewport config) | J12: Medium | K12: Positive | L12: System | M12: BLOCKED
A13: 11 | B13: TC-SEO-011 | C13: SEO & Google Discoverability Testing | D13: Duplicate Content | E13: No duplicate/thin-content issues across near-identical product listings | F13: Multiple sellers may list similar/identical products | G13: 1. Compare product pages for the same generic product across different sellers 2. Check canonical tags | H13: Same product (e.g., 'Amul Fresh Milk 1L') from 2 different sellers | I13: Each seller's product page is distinct where appropriate, or canonical tags correctly indicate the primary version to avoid duplicate-content penalties | J13: Medium | K13: Edge | L13: System | M13: FAIL

Sheet Performance & UX
A1: Performance & User Experience Testing — Test Case Scenarios
A2: S.No | B2: Test Case ID | C2: Module | D2: Sub-Feature / Flow | E2: Test Scenario | F2: Preconditions | G2: Test Steps | H2: Test Data | I2: Expected Result | J2: Priority | K2: Type | L2: Actor / Role | M2: Status
A3: 1 | B3: TC-PERF-001 | C3: Performance & User Experience Testing | D3: Page Load Speed | E3: Home page loads within acceptable time on 4G mobile network | F3: Production/staging environment under typical load | G3: 1. Load home page on a throttled 4G connection 2. Measure time to interactive | H3: 4G network simulation | I3: Home page becomes interactive within the agreed SLA (e.g., <3 seconds) | J3: High | K3: Positive | L3: System | M3: BLOCKED
A4: 2 | B4: TC-PERF-002 | C4: Performance & User Experience Testing | D4: API Response Time | E4: Core order/search APIs respond within SLA under normal load | F4: APIs deployed in a representative test environment | G4: 1. Call product search API and order-placement API 2. Measure response time | H4: Typical query load | I4: 95th percentile response time within agreed SLA (e.g., <500ms for search, <1s for order placement) | J4: High | K4: Positive | L4: System | M4: BLOCKED
A5: 3 | B5: TC-PERF-003 | C5: Performance & User Experience Testing | D5: Search Performance | E5: Search returns results quickly even with a large catalog (lakhs of products) | F5: Catalog seeded with a large representative product volume | G5: 1. Perform text search across a large indexed catalog 2. Measure response time and relevance | H5: Simulated catalog of 100,000+ products | I5: Search remains responsive (within SLA) and returns relevant results without significant degradation at scale | J5: High | K5: Positive | L5: System | M5: BLOCKED
A6: 4 | B6: TC-PERF-004 | C6: Performance & User Experience Testing | D6: Mobile Responsiveness | E6: UI renders correctly across common mobile device sizes | F6: App/site accessible on multiple devices | G6: 1. Open key screens (home, product, cart, checkout) on small, medium, and large mobile viewports | H6: e.g., 360px, 390px, 428px widths | I6: Layout adapts correctly with no overlapping elements, cut-off text, or broken components on any tested size | J6: Medium | K6: Positive | L6: System | M6: BLOCKED
A7: 5 | B7: TC-PERF-005 | C7: Performance & User Experience Testing | D7: Load/Stability Testing | E7: Application remains stable under peak concurrent user load | F7: Load-testing environment configured to simulate concurrent users | G7: 1. Simulate peak concurrent users (e.g., festival sale traffic) placing orders and searching 2. Monitor error rates and response times | H7: Simulated peak load (e.g., 5,000 concurrent users) | I7: No crashes or significant error-rate spikes; response times stay within acceptable degradation limits | J7: High | K7: Positive | L7: System | M7: BLOCKED
A8: 6 | B8: TC-PERF-006 | C8: Performance & User Experience Testing | D8: Scalability | E8: System scales correctly when a new city/vendor set is onboarded at volume | F8: Multi-city architecture in place | G8: 1. Onboard a new city with a batch of sellers and products 2. Monitor system performance during and after onboarding | H8: Bulk onboarding of a new city's sellers | I8: Platform absorbs the new city's data and traffic without performance degradation to existing cities | J8: Medium | K8: Positive | L8: System | M8: BLOCKED
A9: 7 | B9: TC-PERF-007 | C9: Performance & User Experience Testing | D9: Checkout Flow UX | E9: Checkout flow is smooth with no unnecessary friction or broken steps | F9: Standard cart with valid items | G9: 1. Walk through the entire checkout flow (cart -> address -> payment -> confirmation) 2. Note any friction points | H9: Standard multi-item checkout | I9: Checkout completes in a minimal number of clear steps; no dead ends, broken buttons, or confusing states | J9: Medium | K9: Positive | L9: Customer | M9: BLOCKED
A10: 8 | B10: TC-PERF-008 | C10: Performance & User Experience Testing | D10: Image/Media Load | E10: Product and shop images/videos load without excessive delay or layout shift | F10: Shop with images, reels, and store video/tour | G10: 1. Open a shop page with images and video banner 2. Observe load behavior and layout stability | H10: Shop page with mixed media | I10: Media loads progressively without causing significant layout shift (supports good CLS); no broken image placeholders lingering | J10: Medium | K10: Positive | L10: System | M10: BLOCKED

Sheet Order Rescue & Reassignment
A1: Smart Order Rescue & Seller Reassignment — Test Case Scenarios
A2: S.No | B2: Test Case ID | C2: Module | D2: Sub-Feature / Flow | E2: Test Scenario | F2: Preconditions | G2: Test Steps | H2: Test Data | I2: Expected Result | J2: Priority | K2: Type | L2: Actor / Role | M2: Status
A3: 1 | B3: TC-RES-001 | C3: Smart Order Rescue & Seller Reassignment | D3: Rescue Trigger | E3: Seller marks 'Unable to Fulfill' - order routed to Rescue Engine | F3: Order accepted stage; seller cannot fulfill (stock unavailable/shop closed/no response/timeout) | G3: 1. Seller selects 'Unable to Fulfill' with a reason 2. Observe order routing | H3: Reason: Stock Unavailable | I3: Order is automatically routed to the Order Rescue Engine instead of being simply cancelled | J3: High | K3: Positive | L3: Seller/System | M3: PASS
A4: 2 | B4: TC-RES-002 | C4: Smart Order Rescue & Seller Reassignment | D4: Rescue Matching | E4: Rescue Engine finds an alternative seller matching criteria | F4: Order routed to Rescue Engine | G4: 1. System searches nearby sellers by distance, stock, rating, ETA, price 2. Reviews returned candidate list | H4: 3 candidate sellers within configured radius, all in stock | I4: A ranked list of alternative sellers is returned with distance, price, ETA, stock, and rating for each | J4: High | K4: Positive | L4: System | M4: PASS
A5: 3 | B5: TC-RES-003 | C5: Smart Order Rescue & Seller Reassignment | D5: No Seller Available | E5: No alternative seller found within configured radius | F5: Rescue Engine search returns zero eligible sellers | G5: 1. Run rescue search where no seller in range has the item in stock | H5: Search radius = 5 km, no matching seller | I5: System offers: wait for restock, schedule future delivery, partial order, or cancel with refund to wallet/original payment | J5: High | K5: Negative | L5: System | M5: FAIL
A6: 4 | B6: TC-RES-004 | C6: Smart Order Rescue & Seller Reassignment | D6: Auto-Assignment - Same Price | E6: Alternative seller found at same price - auto-assigned without customer approval | F6: Rescue Engine found a matching-price alternative; auto-assign rule enabled | G6: 1. System matches an alternative seller at the same price 2. Auto-assigns the order | H6: Original ₹520, alternative also ₹520 | I6: Order reassigned automatically; customer notified of the seller change only, no approval required since no price impact | J6: High | K6: Positive | L6: System | M6: PASS
A7: 5 | B7: TC-RES-005 | C7: Smart Order Rescue & Seller Reassignment | D7: Reassignment - Higher Price | E7: Alternative seller found at a higher price - requires customer approval | F7: Alternative seller's price exceeds original | G7: 1. System finds an alternative seller priced higher 2. Generates credit note/revised invoice 3. Sends to customer for approval | H7: Original ₹500, alternative ₹540 | I7: Customer must approve and pay the ₹40 difference before the order is assigned to the new seller | J7: High | K7: Positive | L7: System | M7: PASS
A8: 6 | B8: TC-RES-006 | C8: Smart Order Rescue & Seller Reassignment | D8: Reassignment - Lower Price | E8: Alternative seller found at a lower price - auto-refund processed | F8: Alternative seller's price is lower than original | G8: 1. System finds a cheaper alternative seller 2. Auto-processes refund of the difference | H8: Original ₹540, alternative ₹515 | I8: ₹25 automatically refunded to wallet/original payment method; order assigned to new seller without requiring approval | J8: Medium | K8: Positive | L8: System | M8: PASS
A9: 7 | B9: TC-RES-007 | C9: Smart Order Rescue & Seller Reassignment | D9: Super Admin Manual Assignment | E9: Super Admin manually reviews and assigns an alternative seller | F9: Order pending in Rescue Queue; auto-assignment disabled or ambiguous | G9: 1. Super Admin opens 'Order Rescue Queue' 2. Reviews candidate sellers (price/distance/ETA/rating) 3. Manually assigns order to a chosen seller | H9: Multiple viable candidates | I9: Order is reassigned to the Super-Admin-selected seller; decision and reasoning logged | J9: High | K9: Positive | L9: Super Admin | M9: PASS
A10: 8 | B10: TC-RES-008 | C10: Smart Order Rescue & Seller Reassignment | D10: Super Admin Override | E10: Super Admin overrides an auto-assignment with a manual pick | F10: Order already auto-assigned to a candidate | G10: 1. Super Admin opens the auto-assigned order 2. Selects a different seller from the candidate list 3. Confirms override | H10: Auto-assigned to Seller A; Admin reassigns to Seller B | I10: Reassignment updates to Seller B; Seller A is notified the assignment was reversed; audit trail captures the override | J10: Medium | K10: Positive | L10: Super Admin | M10: PASS
A11: 9 | B11: TC-RES-009 | C11: Smart Order Rescue & Seller Reassignment | D11: Configurable Search Radius | E11: Search radius setting correctly limits candidate sellers | F11: Search radius configured to 10 km | G11: 1. Set radius = 10 km 2. Run rescue search with sellers at 8 km and 12 km | H11: Seller X at 8 km, Seller Y at 12 km | I11: Only Seller X (within 10 km) appears as a candidate; Seller Y is excluded | J11: Medium | K11: Edge | L11: System | M11: FAIL
A12: 10 | B12: TC-RES-010 | C12: Smart Order Rescue & Seller Reassignment | D12: Max Price Difference Rule | E12: Reassignment blocked when price difference exceeds configured maximum | F12: Maximum allowed price difference configured (e.g., ₹50) | G12: 1. Rescue Engine finds only a candidate priced ₹80 higher than original 2. Check system behavior | H12: Price difference = ₹80; max allowed = ₹50 | I12: Auto-assignment is blocked; case is routed to Super Admin for manual decision rather than proceeding automatically | J12: High | K12: Edge | L12: System | M12: PASS
A13: 11 | B13: TC-RES-011 | C13: Smart Order Rescue & Seller Reassignment | D13: Seller Notifications | E13: Old seller notified their order has been transferred | F13: Order reassigned away from original seller | G13: 1. Complete a reassignment 2. Check original seller's notifications | H13: Reassigned order | I13: Original seller receives a notification confirming the order was transferred to another seller | J13: Medium | K13: Positive | L13: Seller | M13: FAIL
A14: 12 | B14: TC-RES-012 | C14: Smart Order Rescue & Seller Reassignment | D14: New Seller Acceptance Window | E14: New seller must accept the reassigned order within X minutes | F14: Order newly assigned to an alternative seller | G14: 1. New seller receives assignment notification 2. Observe acceptance countdown/deadline | H14: Acceptance window = 10 minutes | I14: New seller sees a clear time-bound prompt to accept; order pending confirmation until accepted | J14: Medium | K14: Positive | L14: Seller | M14: PASS
... A20: 18 | B20: TC-RES-018 | C20: Smart Order Rescue & Seller Reassignment | D20: Candidate Ranking | E20: Candidate seller ranking factors in rating and cancellation-rate history | F20: Multiple candidates with differing rating/cancellation history | G20: 1. Run rescue search where candidates differ mainly in rating and cancellation rate 2. Review ranking order | H20: Seller A: 4.8 rating, 2% cancellation; Seller B: 4.2 rating, 9% cancellation | I20: Seller A is ranked higher/preferred over Seller B, all else being comparable | J20: Medium | K20: Edge | L20: System | M20: FAIL

Sheet Order Restoration Mgmt
A1: Order Restoration Management System — Test Case Scenarios
A2: S.No | B2: Test Case ID | C2: Module | D2: Sub-Feature / Flow | E2: Test Scenario | F2: Preconditions | G2: Test Steps | H2: Test Data | I2: Expected Result | J2: Priority | K2: Type | L2: Actor / Role | M2: Status
A3: 1 | B3: TC-REST-001 | C3: Order Restoration Management System | D3: Restoration Trigger | E3: Seller unable to fulfill order as originally placed - restoration flow starts | F3: Order accepted; seller cannot fulfill as-is | G3: 1. Seller indicates inability to fulfill 2. System presents restoration options (Modify/Partial Cancel/Reschedule/Price Adjustment) | H3: Standard multi-item order | I3: Seller is presented with all four restoration options rather than a blunt cancellation | J3: High | K3: Positive | L3: Seller | M3: FAIL
A4: 2 | B4: TC-REST-002 | C4: Order Restoration Management System | D4: Modify Order | E4: Seller modifies order (replace item/adjust quantity) - customer approves | F4: Seller selects 'Modify Order' restoration option | G4: 1. Seller replaces unavailable item / adjusts quantity / updates bill 2. Sends to customer 3. Customer approves | H4: 1 item replaced, bill updated | I4: Order continues with modified contents; revised invoice reflects the change | J4: High | K4: Positive | L4: Seller | M4: PASS
A5: 3 | B5: TC-REST-003 | C5: Order Restoration Management System | D5: Modify Order | E5: Seller modifies order - customer rejects the modification | F5: Modification proposed to customer | G5: 1. Customer reviews proposed modification 2. Rejects | H5: Proposed replacement rejected | I5: Modification is not applied; order proceeds to next restoration option or escalates per business rule | J5: High | K5: Negative | L5: Seller | M5: PASS
A6: 4 | B6: TC-REST-004 | C6: Order Restoration Management System | D6: Partial Cancellation | E6: Seller partially cancels unavailable items via restoration flow | F6: Seller selects 'Partial Cancellation' restoration option | G6: 1. Seller removes unavailable items 2. Customer approves 3. Refund issued to wallet 4. Remaining order continues | H6: 2 of 5 items unavailable | I6: Unavailable items removed; wallet refunded for their value; remaining order proceeds without further disruption | J6: High | K6: Positive | L6: Seller | M6: PASS
A7: 5 | B7: TC-REST-005 | C7: Order Restoration Management System | D7: Reschedule Order | E7: Seller reschedules delivery via restoration flow with customer confirmation | F7: Seller selects 'Reschedule Order' restoration option (stock/preparation delay) | G7: 1. Seller/customer proposes a new delivery date 2. Customer confirms 3. Order scheduled to new date | H7: New date within valid delivery window | I7: Order rescheduled and customer receives confirmation of the new delivery date | J7: Medium | K7: Positive | L7: Seller | M7: PASS
A8: 6 | B8: TC-REST-006 | C8: Order Restoration Management System | D8: Price Adjustment - Increase | E8: Price increase via restoration flow generates credit note and requires payment | F8: Seller selects 'Price Adjustment' restoration option with a price increase | G8: 1. Seller generates credit note / revised invoice for the higher price 2. Customer pays the difference 3. Order continues | H8: Price increased by ₹35 | I8: Customer must pay the ₹35 difference before order proceeds; credit note attached to order history | J8: High | K8: Positive | L8: Seller | M8: FAIL
A9: 7 | B9: TC-REST-007 | C9: Order Restoration Management System | D9: Price Adjustment - Decrease | E9: Price decrease via restoration flow auto-refunds to customer wallet | F9: Seller selects 'Price Adjustment' with a price decrease | G9: 1. Seller adjusts bill downward 2. System auto-refunds the difference to customer wallet | H9: Price decreased by ₹20 | I9: ₹20 refunded to wallet automatically; order continues without requiring customer action | J9: Medium | K9: Positive | L9: Seller | M9: PASS
A10: 8 | B10: TC-REST-008 | C10: Order Restoration Management System | D10: Escalation to Super Admin | E10: Seller unable to restore the order - escalates to Super Admin | F10: None of the seller-level restoration options resolve the issue | G10: 1. Seller marks 'Unable to Restore' 2. Case escalates to Super Admin queue | H10: Seller exhausted restoration options | I10: Super Admin receives the escalation with order and seller context for review | J10: High | K10: Positive | L10: Seller/Super Admin | M10: PASS
A11: 9 | B11: TC-REST-009 | C11: Order Restoration Management System | D11: Super Admin Restoration | E11: Super Admin takes restoration action on behalf of the seller | F11: Escalated order in Super Admin queue | G11: 1. Super Admin reviews order & seller info 2. Contacts customer to discuss 3. Performs modify/replace/reschedule/partial-cancel/refund action | H11: Escalated order needing item replacement | I11: Super Admin successfully applies the restoration action on the seller's behalf; action logged under admin identity | J11: High | K11: Positive | L11: Super Admin | M11: PASS
A12: 10 | B12: TC-REST-010 | C12: Order Restoration Management System | D12: Super Admin Revised Invoice | E12: Super Admin generates revised invoice and sends for customer approval | F12: Super Admin has made a restoration change with a price impact | G12: 1. Super Admin generates revised invoice 2. Sends to customer for Approve/Reject | H12: Revised invoice with price impact | I12: Customer receives the revised invoice with a clear Approve/Reject action; order proceeds only upon approval | J12: High | K12: Positive | L12: Super Admin | M12: PASS
A13: 11 | B13: TC-REST-011 | C13: Order Restoration Management System | D13: Customer Rejects Admin Proposal | E13: Customer rejects the Super Admin's revised restoration proposal | F13: Revised invoice sent by Super Admin | G13: 1. Customer reviews the Super Admin's proposal 2. Rejects it | H13: Rejected revised proposal | I13: System proceeds to the next fallback step (retry with original seller, transfer to another seller, or cancel with refund) | J13: High | K13: Negative | L13: Customer | M13: FAIL
A14: 12 | B14: TC-REST-012 | C14: Order Restoration Management System | D14: Still Not Possible Path | E14: Original seller confirmed unable to fulfill even after admin intervention | F14: Super Admin has attempted restoration; original seller still cannot fulfill | G14: 1. Super Admin checks 'Can Original Seller Fulfill?' 2. Result = No | H14: Original seller confirmed unable, post-intervention | I14: System proceeds to transfer the order to another seller rather than looping back to the same seller | J14: Medium | K14: Edge | L14: Super Admin | M14: FAIL
... A19: 17 | B19: TC-REST-017 | C19: Order Restoration Management System | D19: Restoration Status Tracking | E19: Customer can track restoration status throughout the process | F19: Order currently in a restoration flow | G19: 1. Customer opens order 2. Views 'Track Restoration Status' | H19: Order mid-restoration | I19: Customer sees an accurate, up-to-date restoration status (e.g., 'Awaiting Seller Response', 'Escalated to Admin', 'Resolved') | J19: Medium | K19: Positive | L19: Customer | M19: FAIL

Sheet Dashboards & Analytics
A1: Dashboards & Business Analytics (Super Admin / Seller) — Test Case Scenarios
A2: S.No | B2: Test Case ID | C2: Module | D2: Sub-Feature / Flow | E2: Test Scenario | F2: Preconditions | G2: Test Steps | H2: Test Data | I2: Expected Result | J2: Priority | K2: Type | L2: Actor / Role | M2: Status
A3: 1 | B3: TC-DASH-001 | C3: Dashboards & Business Analytics (Super Admin / Seller) | D3: Super Admin KPIs | E3: Platform Overview KPIs match underlying transactional data | F3: Super Admin dashboard accessible with live order/seller/shop data | G3: 1. Note GMV, Total Orders, Active Sellers, Active Shops on dashboard 2. Cross-check against raw order/seller records for the same period | H3: Today's data across all cities | I3: Displayed KPI figures reconcile exactly with underlying database totals for the selected period | J3: High | K3: Positive | L3: Super Admin | M3: PASS
A4: 2 | B4: TC-DASH-002 | C4: Dashboards & Business Analytics (Super Admin / Seller) | D4: Approval Center | E4: Approval Center shows correct pending counts across categories | F4: Pending seller registrations, KYC verifications, shop approvals, and subscription requests exist | G4: 1. Open Approval Center 2. Compare displayed counts to actual pending records in each category | H4: Known pending counts per category | I4: Each category's count (Seller Registrations, KYC, Shop Approvals, Subscription Requests, etc.) matches actual pending records | J4: High | K4: Positive | L4: Super Admin | M4: PASS
A5: 3 | B5: TC-DASH-003 | C5: Dashboards & Business Analytics (Super Admin / Seller) | D5: City Filter | E5: Dashboard correctly filters data when a specific city is selected | F5: Multi-city data available | G5: 1. Change filter from 'All Cities' to a specific city 2. Verify all widgets update to reflect only that city's data | H5: City: Bangalore | I5: Every widget (sales, orders, sellers, logistics) updates consistently to show Bangalore-only figures | J5: High | K5: Positive | L5: Super Admin | M5: PASS
A6: 4 | B6: TC-DASH-004 | C6: Dashboards & Business Analytics (Super Admin / Seller) | D6: Date Filter | E6: Dashboard correctly filters data for a selected date/date range | F6: Historical data available across multiple dates | G6: 1. Change the date filter to a prior date or custom range 2. Verify KPIs and charts update accordingly | H6: Custom range: last 7 days | I6: All widgets reflect only the selected date range's data; 'vs yesterday/previous period' comparisons remain accurate | J6: Medium | K6: Positive | L6: Super Admin | M6: FAIL
A7: 5 | B7: TC-DASH-005 | C7: Dashboards & Business Analytics (Super Admin / Seller) | D7: Data Integrity - Order Status | E7: Order Status breakdown sums correctly to Total Orders | F7: Order Status donut chart displayed with category-wise counts | G7: 1. Sum all displayed order-status categories (New, Accepted, Preparing, Packed, Out for Delivery, Delivered, Cancelled, Returned) 2. Compare to 'Total Orders' figure | H7: Sample: 8,693 total orders across 8 statuses | I7: Sum of all status categories exactly equals the displayed Total Orders count, with no orders unaccounted for | J7: High | K7: Edge | L7: System | M7: PASS
A8: 6 | B8: TC-DASH-006 | C8: Dashboards & Business Analytics (Super Admin / Seller) | D8: Logistics Overview | E8: Logistics Overview correctly splits Platform Logistics vs Self Delivery vs Pickup counts | F8: Orders fulfilled via mixed logistics modes | G8: 1. Open Logistics Overview widget 2. Cross-check counts against actual per-order fulfillment mode | H8: Mixed-mode order set | I8: Platform Logistics, Seller Self Delivery, and Customer Pickup counts each match actual fulfillment records | J8: Medium | K8: Positive | L8: Super Admin | M8: PASS
A9: 7 | B9: TC-DASH-007 | C9: Dashboards & Business Analytics (Super Admin / Seller) | D9: System Health Monitoring | E9: System Health panel accurately reflects live service status | F9: Underlying services (API, Payment Gateway, Notification, Search, Database) monitored | G9: 1. Simulate a service degradation/outage (e.g., payment gateway) 2. Check System Health panel status | H9: Simulated payment gateway outage | I9: Panel reflects the degraded/unhealthy status for the affected service promptly, not a stale 'Healthy' state | J9: High | K9: Edge | L9: Super Admin | M9: PASS
A10: 8 | B10: TC-DASH-008 | C10: Dashboards & Business Analytics (Super Admin / Seller) | D10: AI Insights | E10: AI Insights/Recommendations reflect current, relevant data patterns | F10: Sufficient transactional/inventory data available | G10: 1. Review AI Insights panel (e.g., low-stock alerts, churn risk, demand spikes) 2. Validate against actual underlying data | H10: Known low-stock products / high-demand items | I10: Insights reference real, current conditions (e.g., correct product names, accurate stock/demand figures), not stale or generic text | J10: Low | K10: Positive | L10: Super Admin | M10: PASS
A11: 9 | B11: TC-DASH-009 | C11: Dashboards & Business Analytics (Super Admin / Seller) | D11: Recent Alerts Feed | E11: Recent Alerts update in near real-time as new events occur | F11: Dashboard open; new qualifying event occurs (e.g., new complaint, low stock, payment failure) | G11: 1. Trigger a new alert-worthy event 2. Observe Recent Alerts feed for its appearance and timestamp | H11: New complaint submitted | I11: Alert appears in the feed promptly with an accurate timestamp and correct description | J11: Medium | K11: Positive | L11: Super Admin | M11: FAIL
A12: 10 | B12: TC-DASH-010 | C12: Dashboards & Business Analytics (Super Admin / Seller) | D12: Seller Dashboard - Multi-Store | E12: Seller Dashboard correctly aggregates and separates multi-store performance | F12: Seller owns multiple active stores | G12: 1. Open Seller Dashboard 2. Compare per-store Sales/Orders/Rating figures to each store's actual records | H12: 3 stores with differing performance | I12: Each store's figures are correctly isolated and accurate; combined 'All Stores' totals equal the sum of individual stores | J12: High | K12: Positive | L12: Seller | M12: PASS
A13: 11 | B13: TC-DASH-011 | C13: Dashboards & Business Analytics (Super Admin / Seller) | D13: Seller Financial Reconciliation | E13: Seller Dashboard financial summary reconciles correctly | F13: Seller has revenue, commission, delivery charges, and tax data for the period | G13: 1. Open Financial Summary widget 2. Verify Revenue - Commission - Delivery Charges - Taxes - Other Charges = Net Profit | H13: Revenue ₹1,24,850; Commission ₹12,485; Delivery ₹8,650; Taxes ₹5,230; Other ₹2,150 | I13: Net Profit displayed (₹96,335) matches the manual calculation exactly | J13: High | K13: Positive | L13: Seller | M13: FAIL
A14: 12 | B14: TC-DASH-012 | C14: Dashboards & Business Analytics (Super Admin / Seller) | D14: Assistant Performance Table | E14: Seller Dashboard's Assistant Performance table reflects accurate per-assistant metrics | F14: Multiple assistants have processed orders | G14: 1. Open Assistant Performance table 2. Cross-check Orders/Acceptance Rate/Rating per assistant against actual records | H14: 4 assistants with varying performance | I14: Each assistant's row accurately reflects their individual order count, acceptance rate, and rating | J14: Medium | K14: Positive | L14: Seller | M14: PASS
... A17: 15 | B17: TC-DASH-015 | C17: Dashboards & Business Analytics (Super Admin / Seller) | D17: Business Health Score | E17: Business Health Score recalculates when contributing metrics change | F17: Business Health Score composed of Sales Growth, Satisfaction, Delivery SLA, Stock Availability, Order Acceptance, Response Time | G17: 1. Note current Business Health Score 2. Materially change one contributing metric (e.g., a spike in delivery SLA breaches) 3. Recheck score | H17: Delivery SLA drops from 96% to 80% | I17: Business Health Score recalculates downward to reflect the degraded contributing metric, not a static/stale value | J17: Medium | K17: Positive | L17: Seller/Super Admin | M17: PASS

Sheet UAT Requirement Matrix
A1: UAT — Requirement Traceability Matrix (BRD Coverage)
A2: S.No | B2: Requirement ID | C2: BRD Module / Section | D2: Requirement Description | E2: Acceptance Criteria | F2: Implementation Status | G2: Verified By | H2: Remarks / Gap Identified
A3: 1 | B3: REQ-001 | C3: Order Management | D3: Customer can place Regular, Scheduled, and Pre-Orders | E3: Order created with correct type, status, and delivery-date handling for each order type | F3: Implemented | G3: Jiya | H3: Regular/scheduled/pre-order placement all function correctly with proper status/type handling. | Related: TC-ORD-001, TC-ORD-003, TC-ORD-004, TC-ORD-007
A4: 2 | B4: REQ-002 | C4: Order Management | D4: Customer can modify or cancel an order before seller acceptance | E4: Direct edit/cancel succeeds pre-acceptance; blocked and routed to request-flow post-acceptance | F4: Gap Identified | G4: Jiya | H4: Pre-acceptance direct cancel and post-acceptance approval-routing both work; but customers cannot remove a single line item pre-acceptance (TC-ORD-011) or edit quantity directly (TC-ORD-013) - only full cancel or add-items exist. | Related: TC-ORD-014, TC-ORD-015, TC-ORD-011, TC-ORD-013
A5: 3 | B5: REQ-003 | C5: Partial Order Processing | D5: Seller can partially cancel, replace, split-deliver, or reject unavailable items | E5: All four decision paths function correctly with automatic settlement/invoice recalculation | F5: Gap Identified | G5: Jiya | H5: Split-delivery has no customer confirmation/reject path (TC-PART-004/5/6); replacement rejection never refunds/removes the item (TC-PART-008, TC-ORD-020); approving a priced replacement can leave the order/refund in an inconsistent, unresolved state (TC-PART-011/012). | Related: TC-PART-001, TC-PART-002, TC-PART-003, TC-PART-004, TC-PART-005, TC-PART-006, TC-PART-007, TC-PART-008, TC-PART-009, TC-PART-010, TC-PART-011, TC-PART-012, TC-ORD-020
A6: 4 | B6: REQ-004 | C6: Roles & Permissions | D6: Assistant permission levels (View/Operational/Full Operation) restrict access correctly | E6: Finance, subscription, and assistant-management actions remain blocked at every assistant level | F6: Gap Identified | G6: Jiya | H6: Assistant permission gating largely works, but Finance/Payouts can be delegated to assistants against policy (TC-ROLE-008), there is no disable/re-enable toggle for assistant access (TC-ROLE-011), audit trail does not record which assistant acted (TC-PART-015), and revoked/edited assistant permissions do not invalidate an already-issued JWT (TC-EXC-010, Critical). | Related: TC-ROLE-004, TC-ROLE-005, TC-ROLE-006, TC-ROLE-007, TC-ROLE-008, TC-ROLE-011, TC-PART-015, TC-EXC-010
A7: 5 | B7: REQ-005 | C7: Logistics & Delivery | D7: Seller can configure Pickup / Self-Delivery / Platform Logistics per shop | E7: Configured options reflect accurately at customer checkout; 'No Option Available' state handled gracefully | F7: Gap Identified | G7: Jiya | H7: Core pickup/self-delivery/platform-logistics configuration works; delivery-fee is not seller-configurable (only global schedule) and there is no delivery-exception (failed/customer-unreachable) workflow at all (TC-LOG-015). | Related: TC-LOG-002, TC-LOG-009, TC-LOG-011, TC-LOG-015
A8: 6 | B8: REQ-006 | C8: Subscription & Commission | D8: Seller subscription enforces shop/product limits and auto-expiry/renewal | E8: Shops/products hidden immediately on expiry and restored immediately on renewal | F8: Implemented (Minor Gap) | G8: Jiya | H8: Expiry/limit-enforcement and shop-visibility restore on renewal work correctly; products auto-unpublished at expiry are not auto-republished on renewal (Low gap), and plan upgrades charge full new-plan price with no proration (TC-SUB-011, Medium). | Related: TC-SUB-006, TC-SUB-007, TC-SUB-011, TC-SUB-012, TC-SUB-013
A9: 7 | B9: REQ-007 | C9: Reward Engine | D9: Cashback, coupons, and referral rewards are issued and reversed per configured rules | E9: Reward lifecycle (Created->Active->Redeemed/Expired/Reversed) matches campaign configuration | F9: Gap Identified | G9: Jiya | H9: Cashback/coupon core lifecycle works, but seller-funded cashback cost is never actually deducted from seller settlement (TC-RWD-012, High), there is no fraud/abuse detection for referrals/coupons (TC-RWD-015, High), and seller-to-seller referral rewards are entirely non-functional stub code (TC-SUB-015/TC-INT-012, Critical). | Related: TC-RWD-012, TC-RWD-015, TC-SUB-015, TC-INT-012
A10: 8 | B10: REQ-008 | C10: Pricing & Settlement | D10: Invoice reflects all applicable charge components (GST, delivery, packaging, surcharges) | E10: Invoice breakup matches configured rates; seller settlement nets out commission and adjustments correctly | F10: Gap Identified | G10: Jiya | H10: GST/commission/packaging calculations are correct, but the online pay-difference flow can finalize a price-increase adjustment while collecting Rs.0 from the customer (TC-PRC-011/014, High - real revenue leak); platform fee has no threshold tiering (Medium). | Related: TC-PRC-011, TC-PRC-014, TC-PRC-005, TC-PRC-007, TC-PRC-012
A11: 9 | B11: REQ-009 | C11: Delivery Partner | D11: Delivery partner can accept, navigate, verify (OTP/QR), and confirm delivery | E11: Full delivery workflow completes end-to-end without manual workarounds | F11: Gap Identified | G11: Jiya | H11: OTP-based delivery confirmation and settlement work correctly, but the production delivery-completion route never notifies the seller/admin (TC-E2E-004, High), self-pickup OTP has no attempt lockout (TC-LOG-009), and a rider can go offline mid-active-delivery with no gate (TC-DEL-070, Medium). | Related: TC-LOG-009, TC-DEL-070, TC-E2E-004
A12: 10 | B12: REQ-010 | C12: Finance / Tax Team | D12: Finance/Tax team can access settlement, GST invoices, and tax reports (read/export only) | E12: Role has accurate read/export access to financial data with no operational control access | F12: Gap Identified | G12: Jiya | H12: Finance/Tax (accountant) role is bundled into blanket admin checks with no narrowing - it has unrestricted access to operational screens (product moderation, order status) rather than being read/export-only, and commission/subscription config is not Super-Admin-restricted as required (High/Critical gaps). | Related: TC-ROLE2-008, TC-ROLE2-010, TC-ROLE2-006
A13: 11 | B13: REQ-011 | C13: Operator Role | D13: Operator role exists with a defined, documented scope distinct from Assistant/Super Admin | E13: Operator can monitor/action operational issues across shops without financial or configuration access | F13: Gap Identified | G13: Jiya | H13: The Operator role does not exist anywhere in the codebase (model, middleware, or frontend) - confirmed by repo-wide search. This requirement is entirely unimplemented. | Related: TC-ROLE2-004, TC-ROLE2-005, TC-E2E-006
A14: 12 | B14: REQ-012 | C14: SEO & Discoverability | D14: Shop/product/category pages auto-generate SEO-friendly URLs, meta tags, and schema markup | E14: Pages are crawlable, indexed correctly, and pass structured-data validation | F14: Gap Identified | G14: Jiya | H14: Dynamic SSR for bots, live sitemap, and robots.txt are real and working; but Product/Store JSON-LD is missing required fields (price/availability/address) that would fail Google's Rich Results validation (TC-SEO-003, High). | Related: TC-SEO-003, TC-CAT-001
... A23: 21 | B23: REQ-021 | C23: Dashboards & Analytics | D23: Super Admin and Seller dashboards display accurate, real-time, correctly-scoped KPIs and analytics | E23: All widgets reconcile with underlying data; no cross-seller/cross-city data leakage; filters function correctly | F23: Gap Identified | G23: Jiya | H23: Most dashboard widgets are backed by real, correctly-scoped aggregations, but: two distinct Approval Center categories read the same underlying field and can never diverge (TC-DASH-002), city filter doesn't scope every widget (TC-DASH-003), no custom date-range filtering exists (TC-DASH-004), and per-assistant performance metrics are a hardcoded stub returning null (TC-DASH-012). | Related: TC-DASH-002, TC-DASH-003, TC-DASH-004, TC-DASH-012

Sheet Go-Live Sign-off Checklist
A1: Go-Live / Production Readiness — Sign-off Checklist
A2: S.No | B2: Category | C2: Go-Live Criteria | D2: Status | E2: Blocker? | F2: Owner | G2: Comments
A3: 1 | B3: 1. Requirement Validation (UAT) | C3: Every BRD requirement mapped in the UAT Requirement Matrix is marked Implemented | D3: Not Met | E3: Yes | F3: Product/QA Lead | G3: 16 of 21 BRD requirements are marked Gap Identified, not Implemented (see UAT Requirement Matrix). Requirement Validation is not satisfied.
A4: 2 | B4: 1. Requirement Validation (UAT) | C4: All acceptance criteria validated and signed off by business stakeholders | D4: Pending | E4: TBD | F4: Product Owner | G4: Acceptance-criteria sign-off is a business/product stakeholder action outside the scope of this QA pass.
A5: 3 | B5: 2. Business Flow Testing | C5: End-to-end flows validated for Customer, Seller, Assistant, Delivery Partner, Operator, Finance/Tax, and Super Admin | D5: Not Met | E5: Yes | F5: QA Lead | G5: Operator role does not exist anywhere in the codebase (confirmed by repo-wide search) so its end-to-end flow cannot be validated at all; Finance/Tax (accountant) role is also over-privileged rather than restricted to read/export.
A6: 4 | B6: 2. Business Flow Testing | C6: Cross-role handoff scenarios (order -> fulfillment -> settlement) verified without gaps | D6: Partially Met | E6: Yes | F6: QA Lead | G6: Core order->fulfillment->settlement chain works for Customer/Seller/Delivery/Admin, but cross-role gaps exist: delivery-completion does not notify seller/admin (TC-E2E-004, High), and Super Admin cannot override a seller rejection or force-cancel a stuck order (TC-PART-021/022, High/Critical).
A7: 5 | B7: 3. Feature Validation | C7: Every module tested independently with all business rules, calculations, and validations passing | D7: Not Met | E7: Yes | F7: QA Lead | G7: 110 of 366 test cases failed verification (24 Critical, 37 High severity). See Defects section of the QA report for the full list.
A8: 6 | B8: 4. Role-wise Testing | C8: Role-based permissions and data visibility verified for all 7 roles with no unauthorized access | D8: Not Met | E8: Yes | F8: Security/QA Lead | G8: Operator role missing; accountant role has near-unrestricted admin access; revoked/edited assistant permissions do not invalidate an already-issued JWT (TC-EXC-010, Critical); delivery order-history leaks payment/finance fields to riders (TC-ROLE2-002, High).
A9: 7 | B9: 5. Integration Testing | C9: Data flow verified across Orders, Products, Payments, Logistics, Rewards, Wallet, Notifications, Subscriptions, Settlement | D9: Partially Met | E9: Yes | F9: Tech Lead | G9: Most integrations (payment capture, settlement, reward triggers, notifications) are correctly wired, but cancelling a fully-online-paid order never credits the customer wallet or calls a gateway refund (TC-INT-004, Critical), and seller-to-seller referral rewards never actually credit anything (TC-INT-012, Critical).
A10: 8 | B10: 6. Exception & Negative Testing | C10: Invalid inputs, payment failures, stock shortages, cancellations, refunds, expired subscriptions, and permission violations all handled gracefully | D10: Partially Met | E10: Yes | F10: QA Lead | G10: 7 of 14 Exception & Negative cases FAILed, including: subscription lapse blocks fulfillment of already-paid pre-expiry orders (TC-EXC-009, High), checkout never sends the idempotency key so duplicate-order dedup is dead in practice (TC-EXC-013, High), and mandatory address/pincode validation is missing (TC-EXC-001, High).
A11: 9 | B11: 7. SEO & Discoverability | C11: SEO-friendly URLs, meta tags, schema markup, sitemap, and robots.txt verified | D11: Partially Met | E11: Yes | F11: SEO/Tech Lead | G11: Dynamic SSR for bots, DB-driven sitemap, and robots.txt are real and working; but Product/Store structured data (JSON-LD) is missing required price/availability/address fields needed for Rich Results eligibility (TC-SEO-003, High), and the primary product search uses recency sort, not relevance ranking, on the live path (TC-CAT-001, High).
A12: 10 | B12: 7. SEO & Discoverability | C12: Local SEO ('near me', city/pincode search) and Google Search Console readiness confirmed | D12: Blocked | E12: Yes | F12: SEO/Tech Lead | G12: Requires live Google Search Console access and real-world local search verification against a deployed production domain; deferred to a separate SEO audit.
A13: 11 | B13: 7. SEO & Discoverability | C13: Core Web Vitals and mobile-friendliness meet Google's recommended thresholds | D13: Blocked | E13: Yes | F13: SEO/Tech Lead | G13: Core Web Vitals and mobile-friendliness require live Lighthouse/PageSpeed/Search Console measurement against a deployed environment; deferred to a separate performance audit. Structural note: app is CSR-only for real users (SSR is bot-detected only).
A14: 12 | B14: 8. Performance & UX | C14: Page load speed, API response time, and search performance meet agreed SLA | D14: Blocked | E14: Yes | F14: Tech Lead | G14: Page load / API / search response times require live load-testing infrastructure; no structural performance defects were found in code (proper pagination, debounce, indexing present), but SLA compliance itself cannot be certified without live measurement.
... A19: 17 | B19: 9. Sign-off & Go-Live Readiness | C19: Final production-readiness approval granted by all named owners above | D19: Pending | E19: TBD | F19: Steering Committee | G19: Final go-live approval depends on resolution of the Critical/High defects and completion of the Blocked (live-environment) checks above; not something this review can grant.
A21: FINAL GO / NO-GO DECISION: ______________________ Approved By: ______________________ Date: ______________________

Sheet Execution Log
A1: Test Case ID | B1: Sheet | C1: Scenario | D1: Priority | E1: Type | F1: Actor/Role | G1: Status | H1: Actual Result | I1: Expected Result | J1: Evidence | K1: Defect/Issue | L1: Severity | M1: Failure Scenario | N1: Executed By | O1: Execution Date | P1: Notes
A2: TC-USER-001 | B2: Extras | C2: Register with valid details | D2: High | E2: Functional | F2: User | G2: PASS | H2: Signup flow issues an OTP via issueCustomerOtp() and creates the Customer doc with isVerified:false; verifyCustomerOtpCode() flips isVerified:true and returns a JWT. Account creation is real and persisted. | I2: Account should be created successfully | J2: backend/app/controller/customerAuthController.js:35-53 (signupCustomer), backend/app/services/otpAuthService.js:92-237 (issueCustomerOtp), :239-326 (verifyCustomerOtpCode) | N2: Jiya | O2: 2026-09-17
A3: TC-USER-002 | B3: Extras | C3: Register with existing mobile/email | D3: High | E3: Negative | F3: User | G3: PASS | H3: Duplicate mobile is rejected with 409 'Phone number is already registered. Please login.' when the existing customer is already verified and active; duplicate email is rejected with 409 in both the signup-OTP path and profile update path. | I3: Proper validation message should appear | J3: backend/app/services/otpAuthService.js:124-128 (phone duplicate check), :131-137 and :161-170 (email duplicate check); backend/app/controller/customerAuthController.js:192-204 (profile-update email duplicate + Mongo E11000 fallback at :227-231) | N3: Jiya | O3: 2026-09-17
A4: TC-USER-003 | B4: Extras | C4: Login with valid credentials | D4: High | E4: Functional | F4: User | G4: PASS | H4: Login is phone+OTP based (no password). loginCustomer() requires a pre-existing verified account, sends OTP, verifyCustomerOTP() validates it and issues a 7-day JWT plus records the login activity. | I4: User should log in successfully | J4: backend/app/controller/customerAuthController.js:58-72, 122-162; backend/app/services/otpAuthService.js:118-122 | N4: Jiya | O4: 2026-09-17
A5: TC-USER-004 | B5: Extras | C5: Login with incorrect otp | D5: High | E5: Negative | F5: User | G5: PASS | H5: verifyCustomerOtpCode() hashes the submitted OTP with HMAC-SHA256 and compares to the stored hash; a mismatch returns 400 'Invalid or expired OTP', increments otpFailedAttempts, and locks the account for 15 minutes (423) after 5 failures. | I5: Login should fail | J5: backend/app/services/otpAuthService.js:278-306 (hash compare + failure counter), :11-14 (OTP_MAX_FAILED_ATTEMPTS=5 / OTP_LOCKOUT_MINUTES=15 defaults) | N5: Jiya | O5: 2026-09-17
A6: TC-USER-005 | B6: Extras | C6: Reset password | D6: High | E6: Functional | F6: User | G6: FAIL | H6: The Customer/User model has no password field at all (models/customer.js has no `password` key) and there is no forgot-password/reset-password route, controller, or UI screen anywhere in the customer app. passwordResetService.js only supports role 'seller' and 'admin' (ROLE_CONFIG has no 'customer' entry), so a customer-facing password reset literally cannot be invoked even via the shared service. | I6: Password should be reset successfully | J6: backend/app/models/customer.js:1-167 (no password field); backend/app/services/passwordResetService.js:14-27 (ROLE_CONFIG = {seller, admin} only); no ForgotPassword component found under frontend/src/modules/customer | K6: Customer app has no password-based account, and no forgot-password/reset flow exists for the User role, even though the test case (and the underlying requirement 'reset password for a User account') implies one should. Customer auth is OTP-only by design, so this is either a requirements/scope mismatch or a genuinely missing feature depending on intent. | L6: Low | M6: A user who wants a 'forgot password' recovery flow (e.g. because they conflate OTP login with password auth, or a future release adds password login) has no corresponding screen or API — the feature described by this test case does not exist for the customer role. | N6: Jiya | O6: 2026-09-17 | P6: Re-verified 2026-09-18: still failing — Customer model still has no password field, passwordResetService.js ROLE_CONFIG (line 14-27) still only defines `seller` and `admin`, no customer/user entry, and no ForgotPassword UI exists under frontend/src/modules/customer.
A7: TC-USER-006 | B7: Extras | C7: Update profile | D7: Medium | E7: Functional | F7: User | G7: PASS | H7: updateCustomerProfile() lets a logged-in customer update name/email/addresses/DOB/profileImage/notification prefs, with duplicate-email guard and DOB-in-future validation, then saves and returns the sanitized profile. | I7: Profile should be updated | J7: backend/app/controller/customerAuthController.js:182-238 | N7: Jiya | O7: 2026-09-17
A8: TC-USER-007 | B8: Extras | C8: Add delivery address | D8: High | E8: Functional | F8: User | G8: PASS | H8: AddressesPage.jsx's handleSaveNewAddress() appends a new address object (with geocoded lat/lng) to the customer's addresses array via updateProfile, then refetches and shows it. | I8: Address should be saved | J8: frontend/src/modules/customer/pages/AddressesPage.jsx:129-189; backend/app/controller/customerAuthController.js:205 (addresses assignment) | N8: Jiya | O8: 2026-09-17
A9: TC-USER-008 | B9: Extras | C9: Edit saved address | D9: Medium | E9: Functional | F9: User | G9: PASS | H9: handleUpdateAddress() finds the address by index, merges the edited fields (with re-geocoding) and PATCHes the full addresses array back via updateProfile. | I9: Address should be updated | J9: frontend/src/modules/customer/pages/AddressesPage.jsx:220-291 | N9: Jiya | O9: 2026-09-17
A10: TC-USER-009 | B10: Extras | C10: Delete address | D10: Medium | E10: Functional | F10: User | G10: PASS | H10: handleConfirmDelete() filters out the selected address by index and saves the reduced array via updateProfile. | I10: Address should be deleted | J10: frontend/src/modules/customer/pages/AddressesPage.jsx:322-344 | N10: Jiya | O10: 2026-09-17
A11: TC-USER-010 | B11: Extras | C11: Set default address | D11: Medium | E11: Functional | F11: User | G11: PASS | H11: handleSetDefault() maps every address's isDefault to (index === selected index) before saving, so exactly one address becomes default and the rest are cleared. UI list also renders a 'Default' badge from addr.isDefault. | I11: Selected address becomes default | J11: frontend/src/modules/customer/pages/AddressesPage.jsx:300-318 | N11: Jiya | O11: 2026-09-17
A12: TC-USER-011 | B12: Extras | C12: Search product by name | D12: High | E12: Functional | F12: User | G12: PASS | H12: Product listing supports a `search` query param that regex-matches name/brand/tags/description case-insensitively against real backend data (not a truncated client-side page), consistent with the prior in-store-search fix noted for this app. | I12: Relevant products should appear | J12: backend/app/controller/productController.js:252,273-284 | N12: Jiya | O12: 2026-09-17
A13: TC-USER-012 | B13: Extras | C13: Search with invalid keyword | D13: Medium | E13: Negative | F13: User | G13: PASS | H13: A search term with no regex matches naturally returns an empty items array from the same query path used in TC-011; frontend renders its no-results state off an empty list. | I13: No-result message should appear | J13: backend/app/controller/productController.js:273-284 (same query returns [] when nothing matches) | N13: Jiya | O13: 2026-09-17
A14: TC-USER-013 | B14: Extras | C14: Browse products by category | D14: High | E14: Functional | F14: User | G14: PASS | H14: CategoryProductsPage/backend category filter query real product data by categoryId (server-side), consistent with the previously-fixed subcategory-tab gap noted for this app. | I14: Correct products should appear | J14: frontend/src/modules/customer/pages/CategoryProductsPage.jsx (sort/category wiring); backend/app/controller/productController.js category filter path | N14: Jiya | O14: 2026-09-17
A15: TC-USER-014 | B15: Extras | C15: Filter by price | D15: Medium | E15: Functional | F15: User | G15: FAIL | H15: No price-range filter exists anywhere: productController.js has no minPrice/maxPrice/priceRange query handling, and no Price filter UI (slider, min/max fields) exists in the customer frontend. | I15: Only products within range should appear | J15: grep for minPrice|maxPrice|priceRange across backend/app/controller/*.js and backend/app/routes/*.js returns no matches; grep for the same plus PriceFilter/FilterSheet/FilterModal across frontend/src/modules/customer returns no matches | K15: Filter by price range is not implemented on either the API or the UI. | L15: Medium | M15: A customer wants to narrow results to a ₹500–₹1,000 range on the category/search page; there is no control to do this and no backend parameter it could call even if the UI existed. | N15: Jiya | O15: 2026-09-17 | P15: Re-verified 2026-09-18: still failing — Grep for minPrice/maxPrice/priceRange across backend/app returns only an unrelated match in orderRescueService.js; no price-range filter param or UI exists.
A16: TC-USER-015 | B16: Extras | C16: Filter by brand | D16: Medium | E16: Functional | F16: User | G16: FAIL | H16: No brand filter exists: no BrandFilter component or brand-select control in the customer UI, and while `search` matches the `brand` field via regex, there is no dedicated brand-filter query param or UI control to select a brand from a list. | I16: Selected brand products displayed | J16: grep for BrandFilter/brand filter UI across frontend/src/modules/customer returns no matches; controller/productController.js:281 only touches brand as part of the free-text search regex, not a discrete filter | K16: Dedicated 'select a brand, see only that brand's products' filtering UI/API does not exist (distinct from the free-text search that happens to match the brand field). | L16: Low | M16: A customer wants to tap 'Nike' from a list of brands to filter the product grid; no such control exists, only typing 'Nike' into the search box, which is a materially different UX than the described scenario. | N16: Jiya | O16: 2026-09-17 | P16: Re-verified 2026-09-18: still failing — No BrandFilter component or dedicated brand-filter UI/API found anywhere in frontend/src/modules/customer.
A17: TC-USER-016 | B17: Extras | C17: Sort products by price | D17: Medium | E17: Functional | F17: User | G17: PASS | H17: CategoryFilterBar.jsx exposes a real 'Price: Low to High'/'Price: High to Low' sort control wired to price-asc/price-desc, which productController.js maps to { price: 1 } / { price: -1 } Mongo sorts server-side. | I17: Products sorted correctly | J17: frontend/src/modules/customer/components/shared/CategoryFilterBar.jsx:5-10; backend/app/controller/productController.js:663-664, 1554-1555 | N17: Jiya | O17: 2026-09-17
A18: TC-USER-017 | B18: Extras | C18: View product details | D18: High | E18: Functional | F18: User | G18: PASS | H18: Product detail fetch selects and returns name/mainImage/price/salePrice/description/specifications style fields from the live Product document (same pattern used across hydrateOrderItems/getCustomerVisibleProductById), so the detail page reflects true DB state. | I18: Correct image, name, price, description and specifications displayed | J18: backend/app/services/finance/pricingService.js:781-787 (representative field projection incl. name/price/salePrice/variants) | N18: Jiya | O18: 2026-09-17
A19: TC-USER-018 | B19: Extras | C19: Select product variant | D19: High | E19: Functional | F19: User | G19: PASS | H19: Product variants (sku/name/price/stock) are modeled and consumed consistently through cart, pricing, and stock-reservation code — a selected variantSku is matched against product.variants and its own price/stock is used end-to-end. | I19: Selected variant should be reflected correctly | J19: backend/app/controller/cartController.js:144-159 (variant match on add-to-cart); backend/app/services/finance/pricingService.js:804-817 (variant resolution for pricing); backend/app/services/stockService.js:44-95 (variant-specific stock decrement) | N19: Jiya | O19: 2026-09-17
A20: TC-USER-019 | B20: Extras | C20: Add product to wishlist | D20: Medium | E20: Functional | F20: User | G20: PASS | H20: addToWishlist()/toggleWishlist() controllers exist and persist the wishlist entry for the logged-in customer. | I20: Product should appear in wishlist | J20: backend/app/controller/wishlistController.js:92-127 (addToWishlist), 160+ (toggleWishlist) | N20: Jiya | O20: 2026-09-17
A21: TC-USER-020 | B21: Extras | C21: Remove product from wishlist | D21: Medium | E21: Functional | F21: User | G21: PASS | H21: removeFromWishlist() controller exists to delete a wishlist entry for the logged-in customer. | I21: Product should be removed | J21: backend/app/controller/wishlistController.js:128-159 | N21: Jiya | O21: 2026-09-17
A22: TC-USER-021 | B22: Extras | C22: Add product to cart | D22: High | E22: Functional | F22: User | G22: PASS | H22: addToCart() validates the product is customer-visible and in stock (including per-variant stock) before pushing/incrementing the cart line, rejecting with 400 'out of stock' otherwise. | I22: Product should be added | J22: backend/app/controller/cartController.js:132-267 | N22: Jiya | O22: 2026-09-17
A23: TC-USER-022 | B23: Extras | C23: Add multiple products | D23: High | E23: Functional | F23: User | G23: PASS | H23: Cart items is an array; repeated addToCart calls for different products push additional line items (subject to the documented single-store-per-cart rule, which only removes items from a DIFFERENT seller, not sibling products from the same seller). | I23: All products should appear in cart | J23: backend/app/controller/cartController.js:205-263 (itemIndex push branch), :211-212 (single-seller pruning only cross-seller) | N23: Jiya | O23: 2026-09-17
A24: TC-USER-023 | B24: Extras | C24: Increase quantity | D24: High | E24: Functional | F24: User | G24: PASS | H24: updateQuantity() re-validates current stock (including per-variant) on every increment and rejects with 400 if the requested quantity exceeds available stock, otherwise updates cart.items[i].quantity and re-saves. | I24: Quantity and total should update | J24: backend/app/controller/cartController.js:272-337 | N24: Jiya | O24: 2026-09-17
A25: TC-USER-024 | B25: Extras | C25: Decrease quantity | D25: High | E25: Functional | F25: User | G25: PASS | H25: Same updateQuantity() path handles decrements; a resulting quantity <= 0 splices the line out of the cart instead of leaving a 0-qty row. | I25: Quantity and total should update | J25: backend/app/controller/cartController.js:322-325 | N25: Jiya | O25: 2026-09-17
A26: TC-USER-025 | B26: Extras | C26: Remove product | D26: Medium | E26: Functional | F26: User | G26: PASS | H26: removeFromCart() filters the cart.items array by productId (and optional variantSku) and persists the change. | I26: Product should be removed | J26: backend/app/controller/cartController.js:342-371 | N26: Jiya | O26: 2026-09-17
A27: TC-USER-026 | B27: Extras | C27: Verify cart calculation | D27: High | E27: Functional | F27: User | G27: PASS | H27: Cart subtotal/pricing is never trusted from the client at checkout — buildCheckoutPricingSnapshot/hydrateOrderItems recompute price×quantity from the live Product price server-side (enforceServerPricing:true) before persisting the order breakdown. | I27: Subtotal should be correct | J27: backend/app/services/orderPlacementService.js:560-575 (buildCheckoutPricingSnapshot call); backend/app/services/finance/pricingService.js:819-827 (server-side unit price enforcement) | N27: Jiya | O27: 2026-09-17
A28: TC-USER-027 | B28: Extras | C28: Product becomes out of stock | D28: High | E28: Edge Case | F28: User | G28: PASS | H28: By deliberate design (per prior out-of-stock-visibility audit on this app) an OOS product is intentionally still SHOWN in the cart (flagged) rather than silently removed, but ordering it is hard-blocked: assertAllItemsInStock() re-checks live stock for every cart line right before the atomic order-placement transaction and throws a 409 listing the insufficient items, so checkout cannot proceed. | I28: User should be notified and prevented from ordering | J28: backend/app/services/orderPlacementService.js:249-295 (assertAllItemsInStock, called at :454); backend/app/controller/cartController.js CUSTOMER_VISIBLE_PRODUCT_MATCH (cart still resolves the item, stock enforcement happens at order time) | N28: Jiya | O28: 2026-09-17
... A51: TC-SELL-050 | B51: Extras | C51: Upload valid image | D51: Medium | E51: Functional | F51: Seller | G51: PASS | H51: createProduct()/updateProduct() accept multipart 'mainImage'/'galleryImages' files, upload each to Cloudinary via uploadToCloudinary(), and persist the returned secure URLs onto the product. A normal JPG/PNG upload succeeds through this path. | I51: Image should upload successfully | J51: backend/app/controller/productController.js:864-892,1082-1107 | N51: Jiya | O51: 2026-09-17
A52: TC-SELL-051 | B52: Extras | C52: Upload large image | D52: Medium | E52: Negative | F52: Seller | G52: FAIL | H52: Uploading an oversized image shows no file-size validation anywhere in the path the seller actually uses. The product image multer instance is created with no `limits.fileSize` (backend/app/routes/productRoutes.js:38-39: `const upload = multer({ storage })`), the seller Add/Edit Product frontend performs no client-side size check before submit (no '.size'/'maxSize' reference found in frontend/src/modules/seller/pages/AddProduct.jsx), and uploadToCloudinary() (backend/app/services/mediaService.js:492-520) streams the buffer straight to Cloudinary with no size guard. The only size check that exists in the codebase (validateUploadRequest, mediaService.js:133-183, enforcing getMaxUploadBytes()) belongs to the separate signed-upload-intent flow (/media/upload-intent), which product create/edit does not use. If Cloudinary itself eventually rejects an oversized file, createProduct's upload loop just logs 'Cloudinary upload failed' and continues with that image silently dropped (productController.js:875-878) -- the seller gets no 'file too large' message at all, just a product saved without the image. | I52: Proper file-size validation should appear | J52: backend/app/routes/productRoutes.js:36-39; backend/app/controller/productController.js:864-892,875-878; backend/app/services/mediaService.js:492-520; frontend/src/modules/seller/pages/AddProduct.jsx (no size validation present) | K52: No file-size validation exists on the product-image upload path used by the seller Add/Edit Product screen (neither client-side nor multer-level nor pre-upload server check); failures degrade to a silently dropped image rather than a validation message. | L52: Medium | M52: A seller selects a very large product photo (e.g. 25MB raw camera image) on Add Product and clicks Save. No warning appears client-side; the request reaches createProduct, which attempts the Cloudinary upload. If Cloudinary's account-level limit rejects it, the catch block silently swallows the error and the product is created with no main image and no error shown to the seller, who believes the upload succeeded. | N52: Jiya | O52: 2026-09-17 | P52: Re-verified 2026-09-18: still failing — backend/app/routes/productRoutes.js:39 still `multer({ storage })` with no fileSize limit, AddProduct.jsx has no size validation, and productController.js:924/1142 still silently `console.error` + return null on Cloudinary upload failure with no error surfaced to the seller.
A53: TC-SELL-052 | B53: Extras | C53: Receive new order | D53: High | E53: Functional | F53: Seller | G53: PASS | H53: New orders are created with workflowStatus SELLER_PENDING and appear via getSellerOrders()/fetchSellerOrdersPage scoped to seller:userId, so a freshly placed order shows up in the seller's order list. | I53: New order should appear | J53: backend/app/controller/orderController.js:2280-2317 | N53: Jiya | O53: 2026-09-17
A54: TC-SELL-053 | B54: Extras | C54: Accept order | D54: High | E54: Functional | F54: Seller | G54: PASS | H54: updateOrderStatus() routes seller status:'confirmed' updates through sellerUpdateStatusAtomic (backend/app/services/orderWorkflowService.js:596-600), which calls sellerAcceptAtomic when the order is still SELLER_PENDING, moving the order out of the pending bucket into the accepted workflow state. | I54: Order status should update | J54: backend/app/services/orderWorkflowService.js:566,590-601; backend/app/controller/orderController.js:1054-1072 | N54: Jiya | O54: 2026-09-17
A55: TC-SELL-054 | B55: Extras | C55: Reject order | D55: High | E55: Functional | F55: Seller | G55: PASS | H55: Seller-initiated status:'cancelled' on a still-SELLER_PENDING order routes to sellerRejectAtomic() (orderWorkflowService.js:611-612) after requiring a >=10 char reason, which rejects/cancels the order before any acceptance -- functionally the 'Reject' action. | I55: Order should be rejected | J55: backend/app/services/orderWorkflowService.js:603-613 | N55: Jiya | O55: 2026-09-17
A56: TC-SELL-055 | B56: Extras | C56: Mark order as packed | D56: High | E56: Functional | F56: Seller | G56: PASS | H56: status:'packed' from an accepted seller maps to WORKFLOW_STATUS.PICKUP_READY (or CUSTOMER_PICKUP_READY for pickup orders) via sellerUpdateStatusAtomic's assertTransition() gate (orderWorkflowService.js:691-706), and legacyStatusFromWorkflow maps PICKUP_READY back to the legacy 'packed' status shown across panels. | I56: Order status should update | J56: backend/app/services/orderWorkflowService.js:691-706; backend/app/constants/orderWorkflow.js:71-72 | N56: Jiya | O56: 2026-09-17
A57: TC-SELL-056 | B57: Extras | C57: Add item before packing | D57: High | E57: Edge Case | F57: Seller | G57: PASS | H57: FIXED: added a seller-facing 'Add Item' capability (POST /orders/:orderId/seller-add-items) usable any time before the order is packed (same boundary as the existing customer add-items feature). Unlike the customer version, this does not charge the customer's wallet directly — it goes through the existing propose/customer-approve adjustment flow so the customer explicitly confirms (or pays) the extra amount. | I57: Item should be added and total recalculated | J57: frontend/src/modules/seller/pages/Orders.jsx:851-918 (Adjust editor, existing items only); backend/app/services/orderPriceAdjustmentService.js:753-765 (addItemsToOrder is customer-scoped); backend/app/controller/orderLifecycleController.js:285-298 (route uses req.user.id as customerId) | K57: The 'add item before packing' capability described by this test case does not exist for the Seller role; only the Customer role can add items to an order (via a separate feature), and the seller's own order-adjustment tool can only re-price/re-quantity items already on the order, not add new ones. | L57: Medium | M57: A seller receives a call from a customer asking to add one more item to an unpacked order. The seller opens Order Details -> 'Adjust Price' and finds only the items already on the order editable; there is no way to add the requested extra product, forcing the seller to tell the customer to place a second order or contact support. | N57: Jiya | O57: 2026-09-18 | P57: backend/app/services/orderPriceAdjustmentService.js (sellerAddOrderItems); backend/app/controller/orderLifecycleController.js; backend/app/routes/orderRoutes.js; frontend seller Orders.jsx (Add Item editor). Automated test: __tests__/order-item-self-service-mutations.test.js.
A58: TC-SELL-057 | B58: Extras | C58: Add item after packing | D58: High | E58: Negative | F58: Seller | G58: PASS | H58: Because no seller-facing 'add item' feature exists at all (see TC-SELL-056), a seller cannot add an item to an order regardless of packed state, so the negative expectation ('should prevent it') holds in practice. Separately, the customer-facing addItemsToOrder() explicitly blocks once the order reaches PICKUP_READY/CUSTOMER_PICKUP_READY/OUT_FOR_DELIVERY/DELIVERED/CANCELLED (ADD_ITEMS_BLOCKED_WORKFLOW_STATUSES, orderPriceAdjustmentService.js:29-37,781-786), i.e. blocked once legacy status is 'packed'. Note: the seller/admin item-adjustment path (applyOrderPriceAdjustment, used by 'Adjust Price') is NOT blocked at PICKUP_READY -- it only blocks at CANCELLED/DELIVERED/OUT_FOR_DELIVERY or once a delivery partner is assigned (order.deliveryBoy) -- so a seller could still change quantities/prices on an already-packed order until a rider is assigned. That is a related latent gap but does not affect this specific 'add new item' test since sellers cannot add new items at all. | I58: System should prevent it if not allowed | J58: backend/app/services/orderPriceAdjustmentService.js:29-37,781-786 (customer path, blocked at packed); backend/app/services/orderPriceAdjustmentService.js:236-247 (seller/admin path only blocks at CANCELLED/DELIVERED/OUT_FOR_DELIVERY or deliveryBoy assigned, not at PICKUP_READY/'packed') | N58: Jiya | O58: 2026-09-17
A59: TC-SELL-058 | B59: Extras | C59: View earnings | D59: High | E59: Functional | F59: Seller | G59: PASS | H59: getSellerEarnings() (backend/app/controller/sellerStatsController.js:415-449) queries Transaction with userModel: { $in: ['Seller','Store'] } -- matching the fix noted for the earlier withdrawal-balance bug -- so settled balances, pending payouts and available balance all reflect the seller's actual transactions instead of silently excluding Store-attributed withdrawal rows. | I59: Correct earnings displayed | J59: backend/app/controller/sellerStatsController.js:415-467 | N59: Jiya | O59: 2026-09-17
A60: TC-SELL-059 | B60: Extras | C60: Delivery partner registration | D60: High | E60: Functional | F60: Delivery Partner | G60: PASS | H60: signupDelivery() (backend/app/controller/deliveryAuthController.js:28-119) requires name+phone, uploads profile/aadhar/pan/dl documents, creates or updates the Delivery record with otp/otpExpiry, and sends the OTP -- verifyDeliveryOTP then completes account creation/verification. | I60: Account should be created | J60: backend/app/controller/deliveryAuthController.js:28-119,157-215 | N60: Jiya | O60: 2026-09-17
A61: TC-SELL-060 | B61: Extras | C61: Upload required documents | D61: High | E61: Functional | F61: Delivery Partner | G61: PASS | H61: Document uploads (aadhar/pan/dl) are handled inline in signupDelivery() via Promise.all over req.files, each uploaded to Cloudinary under 'delivery/documents' and stored on delivery.documents. | I61: Documents should upload | J61: backend/app/controller/deliveryAuthController.js:54-68,95-99 | N61: Jiya | O61: 2026-09-17
A62: TC-DEL-061 | B62: Extras | C62: Go online | D62: High | E62: Functional | F62: Delivery Partner | G62: PASS | H62: updateDeliveryProfile() (backend/app/controller/deliveryAuthController.js:279-288) sets delivery.isOnline = true only when the partner is already isVerified, otherwise returns 403 'pending admin verification'. A verified/approved partner can toggle online successfully. | I62: Partner should become available | J62: backend/app/controller/deliveryAuthController.js:279-288 | N62: Jiya | O62: 2026-09-17
A63: TC-DEL-062 | B63: Extras | C63: Receive delivery request | D63: High | E63: Functional | F63: Delivery Partner | G63: PASS | H63: getAvailableOrders() -> fetchAvailableOrdersForDelivery() (backend/app/services/orderQueryService.js:297-420) returns nearby DELIVERY_SEARCH-status orders (and legacy confirmed/packed orders) filtered by the partner's registered location/radius, so a delivery request becomes visible once created for a nearby seller. | I63: Delivery request should appear | J63: backend/app/services/orderQueryService.js:297-420 | N63: Jiya | O63: 2026-09-17
A64: TC-DEL-063 | B64: Extras | C64: Accept delivery | D64: High | E64: Functional | F64: Delivery Partner | G64: PASS | H64: acceptOrder() -> deliveryAcceptAtomic() (backend/app/services/orderWorkflowService.js:878-924) atomically claims the order (deliveryBoy: null guard + skippedBy exclusion) and transitions workflowStatus to DELIVERY_ASSIGNED, so a valid available request is assigned to the accepting partner. | I64: Order assigned to partner | J64: backend/app/services/orderWorkflowService.js:878-924 | N64: Jiya | O64: 2026-09-17
A65: TC-DEL-064 | B65: Extras | C65: Pickup packed order | D65: High | E65: Functional | F65: Delivery Partner | G65: PASS | H65: confirmPickupAtomic() (backend/app/services/orderWorkflowService.js:1698-1733) only allows pickup confirmation from DELIVERY_ASSIGNED/PICKUP_READY states, validates rider lat/lng and seller location, and transitions the order forward (to OUT_FOR_DELIVERY per subsequent code) -- matching legacy status 'Picked Up'. | I65: Order status should change to Picked Up | J65: backend/app/services/orderWorkflowService.js:1698-1733 | N65: Jiya | O65: 2026-09-17
A66: TC-DEL-065 | B66: Extras | C66: Deliver order successfully | D66: High | E66: Functional | F66: Delivery Partner | G66: PASS | H66: verifyHandoffOtpAndDeliver() (backend/app/services/orderWorkflowService.js:1930-1990) requires OUT_FOR_DELIVERY state, validates the OTP, and on match sets workflowStatus/status to DELIVERED with deliveredAt -- the standard successful-delivery completion path. | I66: Order should be marked Delivered | J66: backend/app/services/orderWorkflowService.js:1930-1990 | N66: Jiya | O66: 2026-09-17
A67: TC-DEL-066 | B67: Extras | C67: Complete delivery with valid OTP | D67: High | E67: Functional | F67: Delivery Partner | G67: PASS | H67: Same verifyHandoffOtpAndDeliver() function: a correct OTP (hash match against OrderOtp.codeHash) marks the OTP consumed and the order DELIVERED in one atomic update. | I67: Delivery should complete | J67: backend/app/services/orderWorkflowService.js:1965-1990 | N67: Jiya | O67: 2026-09-17
A68: TC-DEL-067 | B68: Extras | C68: Complete delivery with wrong OTP | D68: High | E68: Negative | F68: Delivery Partner | G68: PASS | H68: An incorrect OTP fails the hash comparison (line 1965-1971), increments otp.attempts, and throws a 400 'Invalid OTP' without touching the order's workflowStatus -- delivery is not completed. Expired OTPs and exceeding maxAttempts are separately rejected (lines 1954-1963). | I68: Delivery should not complete | J68: backend/app/services/orderWorkflowService.js:1954-1971 | N68: Jiya | O68: 2026-09-17
A69: TC-DEL-068 | B69: Extras | C69: View earnings | D69: High | E69: Functional | F69: Delivery Partner | G69: PASS | H69: getDeliveryEarnings() (backend/app/controller/deliveryController.js:100-267) reads Transaction rows filtered by userModel:'Delivery' for the logged-in rider, computing totalEarnings/availableBalance from settled 'Delivery Earning'/'Incentive'/'Bonus' transactions -- matches the fix noted for the earlier delivery-earnings-showed-zero bug (legacy Transaction mirror now populated on delivery). | I69: Correct amount displayed | J69: backend/app/controller/deliveryController.js:100-192 | N69: Jiya | O69: 2026-09-17
A70: TC-DEL-069 | B70: Extras | C70: View delivery history | D70: Medium | E70: Functional | F70: Delivery Partner | G70: PASS | H70: getMyDeliveryOrders() (backend/app/controller/deliveryController.js:522-580+) supports status=all/delivered/cancelled/returns filters and queries orders assigned to the requesting partner (via buildAssignedToPartnerFilter, covering both legacy status and v2 workflowStatus fields), returning an accurate history list. | I70: Correct history displayed | J70: backend/app/controller/deliveryController.js:522-580 | N70: Jiya | O70: 2026-09-17
A71: TC-DEL-070 | B71: Extras | C71: Go offline with active delivery | D71: High | E71: Edge Case | F71: Delivery Partner | G71: FAIL | H71: Going offline has zero restriction anywhere in the stack, even with an active in-progress delivery. Backend: updateDeliveryProfile() (backend/app/controller/deliveryAuthController.js:279-288) only gates the ONLINE direction ('if (isOnline && !delivery.isVerified) return 403'); the offline branch (`delivery.isOnline = isOnline`) has no check for an assigned/active order at all. Frontend: the Dashboard toggle (frontend/src/modules/delivery/pages/Dashboard.jsx:90-95) calls `deliveryApi.updateProfile({ isOnline: newStatus })` directly on tap/swipe with no confirmation dialog and no active-order check beforehand. | I71: System should handle restriction appropriately | J71: backend/app/controller/deliveryAuthController.js:279-288; frontend/src/modules/delivery/pages/Dashboard.jsx:90-95 | K71: A delivery partner can flip themselves offline mid-delivery (order already accepted / picked up / out for delivery) with no warning, confirmation, or system restriction of any kind. | L71: Medium | M71: A rider is en route with a customer's order OUT_FOR_DELIVERY and, wanting to stop taking new work, taps 'Go Offline'. The toggle succeeds immediately and silently -- no confirmation asks about the active delivery, and the rider now appears offline/unavailable for new assignment while still nominally responsible for finishing the current one, with no operational safeguard (e.g. blocking the toggle, or auto re-queuing the order) in place. | N71: Jiya | O71: 2026-09-17 | P71: Re-verified 2026-09-18: still failing — deliveryAuthController.js updateDeliveryProfile() (line 279-288) still only gates the isOnline=true direction against isVerified; the offline branch (`delivery.isOnline = isOnline`) has zero check for an active/assigned order.
A72: TC-ADMIN-071 | B72: Extras | C72: Admin login | D72: High | E72: Functional | F72: Admin | G72: PASS | H72: loginAdmin() (backend/app/controller/adminAuthController.js:125-153) validates credentials, checks password hash, records login, and issues a JWT plus sanitized admin object on success. | I72: Admin dashboard should open | J72: backend/app/controller/adminAuthController.js:125-153 | N72: Jiya | O72: 2026-09-17
A73: TC-ADMIN-072 | B73: Extras | C73: View users | D73: High | E73: Functional | F73: Admin | G73: PASS | H73: getUsers() (backend/app/controller/admin/userController.js:8-20) paginates and returns customer records via getUsersData(); getUserById() fetches a single customer's detail. Both are wired to admin-only routes (backend/app/routes/adminAuth.js:296-297). | I73: User list should display correctly | J73: backend/app/controller/admin/userController.js:8-40; backend/app/routes/adminAuth.js:296-297 | N73: Jiya | O73: 2026-09-17
A74: TC-ADMIN-073 | B74: Extras | C74: Block user | D74: High | E74: Functional | F74: Admin | G74: PASS | H74: RE-VERIFIED FIXED (2026-09-18): userAdminService.js now exports blockUserById()/unblockUserById() (lines 146-165), adminAuth.js registers PUT /users/:id/block and /unblock (lines 309-310), and CustomerDetail.jsx handleRestrictAccount() now calls adminApi.blockUser/unblockUser and updates state only on success. | I74: User should be blocked | J74: backend/app/services/admin/userAdminService.js (no block export); backend/app/routes/adminAuth.js:296-297 (only GET routes registered); frontend/src/modules/admin/pages/CustomerDetail.jsx:105-110,435,505-509 (client-only fake state update, no API call) | K74: 'Block user' in the admin Customer Detail page is a non-functional mock: it flips a local React state variable and shows a success toast, but never calls any backend endpoint, and no backend endpoint to block a customer exists in the first place. | L74: Critical | M74: Admin discovers a fraudulent/abusive customer account and clicks 'Block Account' -> confirms in the modal -> sees 'Account successfully restricted'. The change is never persisted: on page refresh the customer shows as active again, and the customer can continue to log in, browse, and place orders completely uninterrupted -- admin has no real way to block a customer anywhere in the product. | N74: Jiya | O74: 2026-09-18
A75: TC-ADMIN-074 | B75: Extras | C75: Unblock user | D75: High | E75: Functional | F75: Admin | G75: PASS | H75: RE-VERIFIED FIXED (2026-09-18): Same handleRestrictAccount()/unblockUserById() code path as TC-ADMIN-073 now performs a real, persisted unblock via PUT /users/:id/unblock. | I75: User should regain access | J75: frontend/src/modules/admin/pages/CustomerDetail.jsx:105-110; backend/app/services/admin/userAdminService.js (no unblock export); backend/app/routes/adminAuth.js:296-297 | K75: 'Unblock user' is the same fake client-only toggle as 'Block user' -- there is nothing real to unblock since blocking itself was never persisted. | L75: Critical | M75: Since no customer is ever actually blocked server-side (see TC-ADMIN-073), 'unblocking' one is a no-op that only ever affected the admin's own browser tab's local state. | N75: Jiya | O75: 2026-09-18
A76: TC-ADMIN-075 | B76: Extras | C76: Approve seller | D76: High | E76: Functional | F76: Admin | G76: PASS | H76: approveSellerApplicationById() (backend/app/services/admin/sellerApplicationService.js:176-230) sets the Store's isVerified/isActive/isOpen to true and applicationStatus:'approved', plus mirrors verification onto the owner Seller account -- making the seller active and functional. | I76: Seller should become active | J76: backend/app/services/admin/sellerApplicationService.js:176-230 | N76: Jiya | O76: 2026-09-17
A77: TC-ADMIN-076 | B77: Extras | C77: Reject seller | D77: High | E77: Functional | F77: Admin | G77: PASS | H77: rejectSellerApplicationById() (backend/app/services/admin/sellerApplicationService.js:553-593) sets isVerified:false, isActive:false, applicationStatus:'rejected' with a rejectionReason, notifying the seller -- the seller remains inactive/unable to operate. | I77: Seller should remain inactive | J77: backend/app/services/admin/sellerApplicationService.js:553-593 | N77: Jiya | O77: 2026-09-17
A78: TC-ADMIN-077 | B78: Extras | C78: Block seller | D78: High | E78: Functional | F78: Admin | G78: PASS | H78: RE-VERIFIED FIXED (2026-09-18): SellerDetail.jsx "Force Close"/"SUSPEND STORE" buttons now call handleToggleStoreSuspension() (line 451+) which invokes adminApi.suspendStore/reactivateStore, and adminAuth.js registers PUT /sellers/active/:id/suspend and /reactivate (lines 324-325). | I78: Seller should become inactive | J78: frontend/src/modules/admin/pages/SellerDetail.jsx:1015,1030-1038 (buttons with no onClick handler); backend/app/services/admin/sellerApplicationService.js:553-593 (reject is for pending applications only, not active-seller suspension); no seller-suspend route found in backend/app/routes/adminAuth.js | K78: 'Block seller' for an already-active/approved seller is entirely non-functional: the 'Force Close' and 'SUSPEND STORE' buttons on the Seller Detail page have no click handler wired at all, and no backend endpoint exists to deactivate an active store outside of the pending-application reject flow. | L78: Critical | M78: Admin needs to immediately suspend a seller mid-operation for a policy violation (e.g. selling counterfeit goods). Admin opens the seller's detail page and clicks 'SUSPEND STORE' expecting it to immediately hide the store from customers -- nothing happens (no request is sent, no confirmation, no state change) and the seller continues accepting orders unimpeded. | N78: Jiya | O78: 2026-09-18
A79: TC-ADMIN-078 | B79: Extras | C79: View all products | D79: Medium | E79: Functional | F79: Admin | G79: PASS | H79: getProducts() with role==='admin' (backend/app/controller/productController.js:249-520) and getModerationProducts() (lines 1493-1611) both return paginated product listings with full seller/category population for admin use, without the customer-visibility radius/stock filters applied. | I79: Products should be listed | J79: backend/app/controller/productController.js:249-520,1493-1611 | N79: Jiya | O79: 2026-09-17
A80: TC-ADMIN-079 | B80: Extras | C80: Delete product | D80: High | E80: Functional | F80: Admin | G80: PASS | H80: deleteProduct() (backend/app/controller/productController.js:1337-1365) allows role==='admin' to delete any product ({ _id: id } query, bypassing the sellerId ownership check applied to sellers), then removes the search index entry and invalidates relevant caches. | I80: Product should be deleted according to rules | J80: backend/app/controller/productController.js:1337-1365 | N80: Jiya | O80: 2026-09-17
A81: TC-ADMIN-080 | B81: Extras | C81: Add category | D81: High | E81: Functional | F81: Admin | G81: PASS | H81: createCategory() (backend/app/controller/categoryController.js:143-222) whitelists allowed fields, validates the type (header/category/subcategory) and parent hierarchy, enforces a unique slug, uploads an optional image, and creates the Category document. | I81: Category should be created | J81: backend/app/controller/categoryController.js:143-222 | N81: Jiya | O81: 2026-09-17
A82: TC-ADMIN-081 | B82: Extras | C82: Edit category | D82: Medium | E82: Functional | F82: Admin | G82: PASS | H82: updateCategory() (backend/app/controller/categoryController.js:227+) validates the category ObjectId and applies the same whitelisted-field/hierarchy rules as create before persisting the update. | I82: Category should update | J82: backend/app/controller/categoryController.js:227-260 | N82: Jiya | O82: 2026-09-17
A83: TC-ADMIN-082 | B83: Extras | C83: Delete category | D83: High | E83: Functional | F83: Admin | G83: FAIL | H83: deleteCategory() (backend/app/controller/categoryController.js:325-350) recursively deletes the category and all descendant categories (deleteWithChildren), then only invalidates category-name/list caches -- it never touches Product documents that reference the deleted category/subcategory/header IDs. Products keep a categoryId/subcategoryId/headerId pointing at a now-nonexistent Category document; they are not reassigned, flagged, or blocked from deletion, so they silently become orphaned (no error is even surfaced to the admin about how many products are affected). | I83: Category should be deleted/handled correctly | J83: backend/app/controller/categoryController.js:325-350 (no Product query/update at all) | K83: Deleting a category with active products leaves those products with a dangling categoryId/subcategoryId/headerId reference -- the expected result explicitly says 'deleted/handled correctly' but no handling of associated products exists. | L83: Medium | M83: Admin deletes a subcategory that still has 40 live products assigned to it, with no warning about the impact. Those 40 products remain in the database with a categoryId that resolves to nothing -- resolveCategoryName() returns null for them, they vanish from that category's browse/filter view, and there is no admin-facing report or reassignment step to recover or relocate them. | N83: Jiya | O83: 2026-09-17 | P83: Re-verified 2026-09-18: still failing — categoryController.js deleteCategory() (lines 325-350) still only recursively deletes Category docs and invalidates caches; no Product query/update/reassignment of orphaned categoryId/subcategoryId/headerId exists.
A84: TC-ADMIN-083 | B84: Extras | C84: View all orders | D84: High | E84: Functional | F84: Admin | G84: PASS | H84: getSellerOrders() (backend/app/controller/orderController.js:2280-2317), which the admin OrdersList page calls via adminApi.getOrders() -> GET /orders/seller-orders, returns all orders when role==='admin' (message 'All orders fetched') with pagination and a summary block. | I84: Orders should display correctly | J84: backend/app/controller/orderController.js:2280-2317; frontend/src/modules/admin/services/adminApi.js:120 | N84: Jiya | O84: 2026-09-17
A85: TC-ADMIN-084 | B85: Extras | C85: Filter orders | D85: Medium | E85: Functional | F85: Admin | G85: PASS | H85: The same getSellerOrders() endpoint accepts startDate/endDate/status query params and passes them into fetchSellerOrdersPage(), which filters the order query accordingly for both status and createdAt date-range matches. | I85: Matching orders should display | J85: backend/app/controller/orderController.js:2283-2298 | N85: Jiya | O85: 2026-09-17
A86: TC-ADMIN-085 | B86: Extras | C86: View payment transactions | D86: High | E86: Functional | F86: Admin | G86: PASS | H86: getAdminFinanceLedgerController()/getAdminRefundsController() (backend/app/controller/adminFinanceController.js:71,317) expose ledger/transaction and refund listings for the admin Payments views, backed by real Transaction/Refund collections. | I86: Correct transaction details displayed | J86: backend/app/controller/adminFinanceController.js:71,317 | N86: Jiya | O86: 2026-09-17
A87: TC-ADMIN-086 | B87: Extras | C87: Process refund | D87: High | E87: Functional | F87: Admin | G87: PASS | H87: Return/refund approval flows through approveReturnRequest()/updateReturnQcStatus()/completeReturnAndRefund() (backend/app/controller/orderController.js:1291,1492,1812), which require an admin manual QC pass before releasing the refund -- an intentional gate confirmed working correctly in prior review (restocking-fee, GST-reversal, and seller-clawback precision issues in this same refund path were previously identified and fixed). | I87: Refund should be processed correctly | J87: backend/app/controller/orderController.js:1291-1425,1492-1579,1812-2173 | N87: Jiya | O87: 2026-09-17
A88: TC-ADMIN-087 | B88: Extras | C88: Create coupon | D88: High | E88: Functional | F88: Admin | G88: PASS | H88: createCoupon() (backend/app/controller/couponController.js:74-95) creates a Coupon document from admin-provided fields; listCoupons()/updateCoupon()/deleteCoupon() round out full CRUD. | I88: Coupon should be created | J88: backend/app/controller/couponController.js:16-130 | N88: Jiya | O88: 2026-09-17
A89: TC-ADMIN-088 | B89: Extras | C89: Apply coupon conditions | D89: High | E89: Functional | F89: Admin | G89: PASS | H89: applySingleCoupon() (backend/app/services/couponApplicationService.js:15-150+) enforces isActive/validFrom/validTill window, per-user and global usage limits, minOrderValue, minItems, and category-based eligibility -- a coupon configured with a minimum order value or expiry genuinely only applies when those conditions are met, rejecting otherwise with a specific error message. | I89: Coupon should work only under configured conditions | J89: backend/app/services/couponApplicationService.js:38-143 | N89: Jiya | O89: 2026-09-17
A90: TC-ADMIN-089 | B90: Extras | C90: View sales report | D90: Medium | E90: Functional | F90: Admin | G90: PASS | H90: RE-VERIFIED FIXED (2026-09-18): AdvancedAnalytics.jsx now imports adminApi and calls getAnalyticsReport({range: timeRange}) on load/range-change (fetchReport, lines 49-69) with a backed GET /analytics/report route, and handleDownloadReport now calls a real exportFinanceStatement API and downloads a blob instead of a fake setTimeout. | I90: Correct sales report should appear | J90: frontend/src/modules/admin/pages/AdvancedAnalytics.jsx:1-78 (no API import/call anywhere in the file; hardcoded salesData/categoryData/hourlyHeatmap arrays); handleDownloadReport at lines 41-46 (fake setTimeout-only 'download') | K90: The Sales Report / Advanced Analytics screen shows completely fabricated, static numbers unrelated to real orders in the database; selecting a date range and clicking 'Generate'/download does not query the backend at all. | L90: Critical | M90: Admin selects a custom date range to check last quarter's actual revenue and order volume before a board meeting, sees numbers that look plausible (Mon 45000 revenue, Tue 52000, ...), and reports them as real figures -- but these are hardcoded placeholder values that never reflect the platform's actual sales regardless of what range is picked or how much real revenue changed. | N90: Jiya | O90: 2026-09-18
A91: TC-ADMIN-090 | B91: Extras | C91: Verify dashboard statistics | D91: High | E91: Functional | F91: Admin | G91: PASS | H91: getAdminStats()/getAdminDashboard() (backend/app/controller/admin/dashboardController.js:6-34) call getAdminDashboardStats()/getAdminDashboardOverview(), which run real DB aggregations (cached for 5 minutes via getOrSet for performance) over Orders/Users/Sellers, so the numbers genuinely reflect actual data (unlike the fabricated Analytics page in TC-ADMIN-089). | I91: Dashboard numbers should match actual data | J91: backend/app/controller/admin/dashboardController.js:6-34 | N91: Jiya | O91: 2026-09-17
A92: TC-E2E-091 | B92: Extras | C92: User purchases product | D92: High | E92: End-to-End | F92: All Roles | G92: PASS | H92: The full order → seller-accept → pack → delivery-pickup → deliver chain is implemented as a real workflow state machine (workflowStatus progressing SELLER_PENDING → ... → DELIVERED) with each transition emitting the corresponding notification event, verified individually across TC-030/031/033 (placement) and TC-099 (per-stage notifications). | I92: Order should complete successfully | J92: backend/app/services/orderWorkflowService.js (ORDER_CONFIRMED/ORDER_PACKED/OUT_FOR_DELIVERY/ORDER_DELIVERED emission sites at lines 387,776,784,793,1683,1777,2016) | N92: Jiya | O92: 2026-09-17
A93: TC-E2E-092 | B93: Extras | C93: Cancel order before shipment | D93: High | E93: End-to-End | F93: User/Seller/Admin | G93: PASS | H93: Cancellation writes a single authoritative Order document (status/workflowStatus/cancelledBy/cancelReason) read by all three panels via the same resolveOrderStatus()/displayStatus resolver noted in this app's single-source-of-truth fix, and emits ORDER_CANCELLED to both customer and seller sides — status is not independently tracked per role. | I93: Order should be cancelled and status synchronized | J93: backend/app/controller/orderController.js:660-673 | N93: Jiya | O93: 2026-09-17
A94: TC-E2E-093 | B94: Extras | C94: Return delivered product | D94: High | E94: End-to-End | F94: User/Seller/Admin | G94: PASS | H94: Return lifecycle is a real multi-step workflow: requestReturn() (customer) -> approveReturnRequest/rejectReturnRequest (seller/admin) -> assignReturnDelivery/acceptReturnPickup -> updateReturnQcStatus (admin QC gate, confirmed by prior QC-gate audit on this app) -> completeReturnAndRefund(), each step persisted on the Order and notified via RETURN_* events. | I94: Return should be processed successfully | J94: backend/app/controller/orderController.js:1291 (approveReturnRequest), 1426 (rejectReturnRequest), 1492 (updateReturnQcStatus), 1579 (assignReturnDelivery), 1812 (completeReturnAndRefund) | N94: Jiya | O94: 2026-09-17
A95: TC-E2E-094 | B95: Extras | C95: Click payment button multiple times | D95: High | E95: Edge Case | F95: User | G95: PASS | H95: placeOrder() requires an Idempotency-Key header; placeOrderAtomic() checks/locks that key (checkIdempotency/acquireIdempotencyLock) before doing any work, and a repeat call with the same key returns the already-created order marked duplicate:true instead of creating a second order/payment. A concurrent second click while the first is mid-flight gets 409 'Request is being processed'. | I95: Only one payment/order should be created | J95: backend/app/services/orderPlacementService.js:374-422 (idempotency check/lock), :204-209 (idempotencyKey read from request header in orderController.js) | N95: Jiya | O95: 2026-09-17
A96: TC-E2E-095 | B96: Extras | C96: Two users order last available item | D96: High | E96: Edge Case | F96: User/Seller | G96: PASS | H96: reserveStockForItems() decrements stock with an atomic MongoDB findOneAndUpdate guarded by `stock: {$gte: quantity}` inside the same multi-document transaction session used for order creation. If stock=1 and two orders race, only one findOneAndUpdate can match the $gte condition and succeed; the loser gets `updated === null` and the code throws a 409 'Insufficient stock', aborting that transaction. | I96: Only one valid order should be accepted | J96: backend/app/services/stockService.js:79-108 (non-variant atomic decrement with $gte guard and null-result rejection at :103-107) | N96: Jiya | O96: 2026-09-17
A97: TC-E2E-096 | B97: Extras | C97: Product becomes out of stock during checkout | D97: High | E97: Edge Case | F97: User/Seller | G97: PASS | H97: Same assertAllItemsInStock() pre-check used for TC-027 covers this scenario generally: if a seller zeroes stock after the item was added to cart, the pre-transaction stock check (and the atomic $gte decrement as a second line of defense) rejects the order with 409 and a message identifying which item is out of stock, rather than silently proceeding. | I97: User should be notified and order should not proceed | J97: backend/app/services/orderPlacementService.js:249-295 | N97: Jiya | O97: 2026-09-17
A98: TC-E2E-097 | B98: Extras | C98: Seller changes product price after cart addition | D98: High | E98: Edge Case | F98: User/Seller | G98: PASS | H98: Order pricing is never taken from the cart's stored priceSnapshot at checkout — hydrateOrderItems() with enforceServerPricing:true always re-reads the CURRENT Product.salePrice/price (or variant price) at order-placement time, so a seller price change between add-to-cart and checkout is applied consistently (the new price wins, matching standard e-commerce behavior), not a stale cached price. | I98: System should apply configured pricing rule consistently | J98: backend/app/services/finance/pricingService.js:819-827 | N98: Jiya | O98: 2026-09-17
A99: TC-E2E-098 | B99: Extras | C99: Verify status synchronization | D99: High | E99: End-to-End | F99: All Roles | G99: PASS | H99: resolveOrderStatus() (backend/app/services/orderStatusResolver.js:121+) is now the single source of truth for the customer-facing displayStatus field, replacing the previous 4-way status-label drift across customer/seller/admin/delivery panels (each panel independently derived a label before). Updates from seller (accept/pack) or delivery (pickup/deliver) both write into the same order.workflowStatus/status fields consumed by this resolver, so all panels reading displayStatus stay consistent. | I99: Status should remain consistent across all panels | J99: backend/app/services/orderStatusResolver.js:121+; backend/app/constants/orderWorkflow.js (shared WORKFLOW_STATUS enum consumed by seller, delivery and admin write paths) | N99: Jiya | O99: 2026-09-17
A100: TC-E2E-099 | B100: Extras | C100: Verify order notifications | D100: High | E100: End-to-End | F100: All Roles | G100: PASS | H100: All 5 lifecycle notification events (ORDER_PLACED, ORDER_CONFIRMED, ORDER_PACKED, OUT_FOR_DELIVERY, ORDER_DELIVERED) are defined and are actually emitted at their corresponding controller/service transitions (accept, pack, ship, deliver), not just declared-but-unused constants. | I100: Correct notifications should be sent at each stage | J100: backend/app/modules/notifications/notification.constants.js:1-7; emission sites confirmed via grep across controller/orderController.js:1154,1176,1185,1202 and services/orderWorkflowService.js:387,776,784,793,1683,1777,2016 | N100: Jiya | O100: 2026-09-17
A101: TC-E2E-100 | B101: Extras | C101: Verify unauthorized panel access | D101: High | E101: Security | F101: All Roles | G101: PASS | H101: Two independent layers enforce role isolation: (1) route-level `verifyToken` + `allowRoles(...)` middleware on every sensitive route (e.g. seller-only order actions require allowRoles('admin','seller') plus requireApprovedSeller/requireBusinessModelChosen), and (2) object-level ownership checks inside handlers — getOrderDetails() explicitly computes isOwnerCustomer/isOwnerSeller/isAssignedDeliveryBoy/isAdmin and returns 403 'Access denied. You are not authorized to view this order.' for anyone else, even if they hold a valid JWT for a different account/role. JWT itself is verified with jwt.verify() against JWT_SECRET and password-reset-purpose tokens are explicitly rejected from being used as session tokens. | I101: Unauthorized functions should be inaccessible | J101: backend/app/middleware/authMiddleware.js:92-119 (verifyToken), 146-157 (allowRoles); backend/app/routes/orderRoutes.js:122,137-177 (route guards); backend/app/controller/orderController.js:519-568 (per-object ownership/data-isolation check) | N101: Jiya | O101: 2026-09-17
A102: TC-ORD-001 | B102: Customer Order Mgmt | C102: Place a regular order successfully | D102: High | E102: Positive | F102: Customer | G102: PASS | H102: placeOrderAtomic validates cart/stock, checks store open, creates Order with workflowStatus SELLER_PENDING/legacyStatus 'pending', fires ORDER_PLACED to customer and NEW_ORDER to seller for COD (ONLINE on capture). Order persisted/queryable via order-history endpoints. | I102: Order placed successfully; status = 'Order Placed'; seller receives order notification; order visible in customer order history | J102: backend/app/services/orderPlacementService.js:363-923,898-915; backend/app/controller/cartController.js:193-203; backend/app/services/orderStatusResolver.js:36-45 | N102: Jiya | O102: 2026-09-17
... A108: TC-ORD-007 | B108: Customer Order Mgmt | C108: Place a pre-order within an active campaign window | D108: High | E108: Positive | F108: Customer | G108: PASS | H108: validatePreorderPlacement requires campaign active/sale_started and now within saleWindow; validateScheduleSelection requires deliveryDate within campaign.deliveryWindow. On success reserves allocation, sets PREORDER_HOLD/'preorder_confirmed', emits PREORDER_CONFIRMED. | I108: Order confirmed; awaits campaign sale-start date; delivery scheduled within campaign window only | J108: backend/app/services/preOrderCampaignService.js:851-908,817-840; backend/app/services/orderPlacementService.js:652-674; backend/app/services/orderSchedulingService.js:119-143 | N108: Jiya | O108: 2026-09-17
